Workbook
Name _REN60: '[1]imp g.o.'!#REF!
Name _UVT2010: #REF!
Name ANEXOS: #REF!
Name ANEXOS4: #REF!
Name BALANCE1: #REF!
Name COD_REPRES: #N/A
Name dirmanualuser: #REF!
Name ESTADO: #REF!
Name SALDOS: #REF!
Name validalog: #REF!

Sheet Calendario Tributario
A1: DECLARACIÓN DE RENTA Y COMPLEMENTARIOS
A3: Personas naturales y sucesiones ilíquidas
A5: Declaración y pago
A7: Últimos 2 dígito del NIT | B7: Fecha límite | D7: Últimos 2 dígito del NIT | E7: Fecha límite | G7: Últimos 2 dígito del NIT | H7: Fecha límite | J7: Últimos 2 dígito del NIT | K7: Fecha límite | M7: Últimos 2 dígito del NIT | N7: Fecha límite
A8: 01 Y 02 | B8: 46246 | D8: 21 Y 22 | E8: 46261 | G8: 41 Y 42 | H8: 46275 | J8: 61 Y 62 | K8: 46289 | M8: 81 Y 82 | N8: 46308
A9: 03 Y 04 | B9: 46247 | D9: 23 Y 24 | E9: 46262 | G9: 43 Y 44 | H9: 46276 | J9: 63 Y 64 | K9: 45925 | M9: 83 Y 84 | N9: 46309
A10: 05 Y 06 | B10: 46248 | D10: 25 Y 26 | E10: 46265 | G10: 45 Y 46 | H10: 46279 | J10: 65 Y 66 | K10: 46293 | M10: 85 Y 86 | N10: 46310
A11: 07 Y 08 | B11: 46252 | D11: 27 Y 28 | E11: 46266 | G11: 47 Y 48 | H11: 46280 | J11: 67 Y 68 | K11: 46296 | M11: 87 Y 88 | N11: 46311
A12: 09 Y 10 | B12: 46253 | D12: 29 Y 30 | E12: 46267 | G12: 49 Y 50 | H12: 46281 | J12: 69 Y 70 | K12: 46297 | M12: 89 Y 90 | N12: 46314
A13: 11 Y 12 | B13: 46254 | D13: 31 Y 32 | E13: 46268 | G13: 51 Y 52 | H13: 46282 | J13: 71 Y 72 | K13: 46300 | M13: 91 Y 92 | N13: 46315
A14: 13 Y 14 | B14: 46255 | D14: 33 Y 34 | E14: 46269 | G14: 53 Y 54 | H14: 46283 | J14: 73 Y 74 | K14: 46301 | M14: 93 Y 94 | N14: 46316
A15: 15 Y 16 | B15: 46258 | D15: 35 Y 36 | E15: 46272 | G15: 55 Y 56 | H15: 46286 | J15: 75 Y 76 | K15: 46302 | M15: 95 Y 96 | N15: 46317
A16: 17 Y 18 | B16: 46259 | D16: 37 Y 38 | E16: 46273 | G16: 57 Y 58 | H16: 46287 | J16: 77 Y 78 | K16: 46303 | M16: 97 Y 98 | N16: 46318
A17: 19 Y 20 | B17: 46260 | D17: 39 Y 40 | E17: 46274 | G17: 59 Y 60 | H17: 46288 | J17: 79 Y 80 | K17: 46304 | M17: 99 Y 00 | N17: 46321
B21: 01 | C21: =B8 -> 46246
B22: 02 | C22: =C21 -> 46246
B23: 03 | C23: =B9 -> 46247
B24: 04 | C24: =C23 -> 46247
B25: 05 | C25: =B10 -> 46248
B26: 06 | C26: =C25 -> 46248
B27: 07 | C27: =B11 -> 46252
B28: 08 | C28: =C27 -> 46252
B29: 09 | C29: =B12 -> 46253
B30: 10 | C30: =C29 -> 46253
B31: 11 | C31: =B13 -> 46254
B32: 12 | C32: =C31 -> 46254
B33: 13 | C33: =B14 -> 46255
B34: 14 | C34: =C33 -> 46255
B35: 15 | C35: =B15 -> 46258
B36: 16 | C36: =C35 -> 46258
B37: 17 | C37: =B16 -> 46259
B38: 18 | C38: =C37 -> 46259
B39: 19 | C39: =B17 -> 46260
B40: 20 | C40: =C39 -> 46260
B41: 21 | C41: =E8 -> 46261
B42: 22 | C42: =C41 -> 46261
B43: 23 | C43: =E9 -> 46262
B44: 24 | C44: =C43 -> 46262
B45: 25 | C45: =E10 -> 46265
B46: 26 | C46: =C45 -> 46265
B47: 27 | C47: =E11 -> 46266
B48: 28 | C48: =C47 -> 46266
B49: 29 | C49: =E12 -> 46267
B50: 30 | C50: =C49 -> 46267
B51: 31 | C51: =E13 -> 46268
B52: 32 | C52: =C51 -> 46268
B53: 33 | C53: =E14 -> 46269
B54: 34 | C54: =C53 -> 46269
B55: 35 | C55: =E15 -> 46272
B56: 36 | C56: =C55 -> 46272
B57: 37 | C57: =E16 -> 46273
B58: 38 | C58: =C57 -> 46273
B59: 39 | C59: =E17 -> 46274
B60: 40 | C60: =C59 -> 46274
B61: 41 | C61: =H8 -> 46275
B62: 42 | C62: =C61 -> 46275
B63: 43 | C63: =H9 -> 46276
B64: 44 | C64: =C63 -> 46276
B65: 45 | C65: =H10 -> 46279
B66: 46 | C66: =C65 -> 46279
B67: 47 | C67: =H11 -> 46280
B68: 48 | C68: =C67 -> 46280
B69: 49 | C69: =H12 -> 46281
B70: 50 | C70: =C69 -> 46281
B71: 51 | C71: =H13 -> 46282
B72: 52 | C72: =C71 -> 46282
B73: 53 | C73: =H14 -> 46283
B74: 54 | C74: =C73 -> 46283
B75: 55 | C75: =H15 -> 46286
B76: 56 | C76: =C75 -> 46286
B77: 57 | C77: =H16 -> 46287
B78: 58 | C78: =C77 -> 46287
B79: 59 | C79: =H17 -> 46288
B80: 60 | C80: =C79 -> 46288
B81: 61 | C81: =K8 -> 46289
B82: 62 | C82: =C81 -> 46289
B83: 63 | C83: =K9 -> 45925
B84: 64 | C84: =C83 -> 45925
B85: 65 | C85: =K10 -> 46293
B86: 66 | C86: =C85 -> 46293
B87: 67 | C87: =K11 -> 46296
B88: 68 | C88: =C87 -> 46296
B89: 69 | C89: =K12 -> 46297
B90: 70 | C90: =C89 -> 46297
B91: 71 | C91: =K13 -> 46300
B92: 72 | C92: =C91 -> 46300
B93: 73 | C93: =K14 -> 46301
B94: 74 | C94: =C93 -> 46301
B95: 75 | C95: =K15 -> 46302
B96: 76 | C96: =C95 -> 46302
B97: 77 | C97: =K16 -> 46303
B98: 78 | C98: =C97 -> 46303
B99: 79 | C99: =K17 -> 46304
B100: 80 | C100: =C99 -> 46304
B101: 81 | C101: =N8 -> 46308
B102: 82 | C102: =C101 -> 46308
B103: 83 | C103: =N9 -> 46309
B104: 84 | C104: =C103 -> 46309
B105: 85 | C105: =N10 -> 46310
B106: 86 | C106: =C105 -> 46310
...

Sheet Datos del contribuyente
B6: Numero de identificación tributaria | C6: 1015670654
B7: DV | C7: 1
B8: Primer apellido | C8: Vasquez
B9: Segundo apellido | C9: Florez
B10: Primer Nombre | C10: Zorani
B11: Otros Nombres | C11: Diana
B12: Actividad Económica | C12: 7490
B13: Corrección - De ser afirmativo marque x
B14: No. formulario Anterior
B15: Fecha de presentación | C15: =VLOOKUP(RIGHT(C6,2),'Calendario Tributario'!$B$21:$C$120,2,0) -> 46283 | D15: No digitar fecha - Automático

Sheet FORMULARIO 210
G2: Declaración de renta y complementarios personas naturales y asimiladas residentes y sucesiones ilíquidas de causantes residentes | AA2: 210 | AH2: Concepto | AI2: Reng | AJ2: Valor
AH3: Ingresos brutos por rentas de trabajo | AJ3: =H15 -> 260333000
AH4: Ingreso Rentas por honorarios | AJ4: =M15 -> 190000000
AH5: Ingresos brutos por rentas de capital | AJ5: =S15 -> 109421000
B6: ACCESO: | P6: CLAVE FIRMA: | AH6: Ingresos brutos por rentas no laborales | AJ6: =Z15 -> 322000000
AH7: Total ingresos brutos | AJ7: =SUM(AJ3:AJ6) -> 881754000
AH8: (-) I.N.C.R.N.G.O. | AJ8: =H17 -> 14400000
B9: Datos declarante | C9: 5. Numero de identificación tributaria (NIT) | K9: 6. DV | L9: 7. Primer apellido | Q9: 8. Segundo apellido | V9: 9. Primer nombre | Z9: 10. Otros nombres | AB9: 12. Cod Dir | AH9: (-) I.N.C.R.N.G.O. | AJ9: =M17 -> 22300000
C10: ='Datos del contribuyente'!C6 -> 1015670654 | K10: ='Datos del contribuyente'!C7 -> 1 | L10: ='Datos del contribuyente'!C8 -> Vasquez | Q10: ='Datos del contribuyente'!C9 -> Florez | V10: ='Datos del contribuyente'!C10 -> Zorani | Z10: ='Datos del contribuyente'!C11 -> Diana | AH10: (-) I.N.C.R.N.G.O. | AJ10: =S17 -> 15112000
AH11: (-) I.N.C.R.N.G.O. | AJ11: =Z17 -> 233000000
B12: 24. Actividad economica | F12: ='Datos del contribuyente'!C12 -> 7490 | G12: Si es una correción indique: 25. Cod | J12: ='Datos del contribuyente'!C13 -> 0 | K12: 26. N° del formulario anterior | O12: ='Datos del contribuyente'!C14 -> 0 | P12: 27. fraccion año gravable siguiente | W12: 28. Uno porciento (1%) de compras con factura electronica | AB12: =ROUND('Fac. Elctrónicas'!D29,-3) -> 1800000
B13: Patrimonio | F13: Patrimonio bruto | K13: 29 | L13: ='Pat bruto'!G119 -> 4540790000 | P13: Deudas | R13: 30 | S13: =Deudas!D2 -> 410000000 | V13: Total patrimonio líquido | Y13: 31 | Z13: =IF(L13>S13,L13-S13,0) -> 4130790000 | AH13: (-) Devoluciones, rebajas, descuentos | AJ13: =+Z16 -> 0
B14: Cédula general | C14: Conceptos / renta | G14: Rentas de trabajo | L14: Rentas de trabajo que no provengan de una relacion laboral o legal y reglamentaria | R14: Rentas de capital | Y14: Rentas no laborales | AH14: (-) Rentas exentas no limitadas | AJ14: ='R.trabajo y honorarios'!F54+'R.trabajo y honorarios'!G58+'R.trabajo y honorarios'!G59+'R.trabajo y honorarios'!G60+'R.trabajo y honorarios'!G61+'R.no laboral y R gravables'!F66 -> 0
C15: Ingresos brutos | G15: 32 | H15: ='R.trabajo y honorarios'!H4 -> 260333000 | L15: 43 | M15: ='R.trabajo y honorarios'!L4 -> 190000000 | R15: 58 | S15: ='R.capital'!G2 -> 109421000 | Y15: 74 | Z15: ='R.no laboral y R gravables'!G3 -> 322000000 | AH15: (=) Base límite del 40% | AJ15: =AJ7-AJ8-AJ9-AJ10-AJ13-AJ14-AJ11 -> 596942000
C16: Devoluciones, rebajas y descuentos | Y16: 75 | Z16: ='R.no laboral y R gravables'!G18 -> 0 | AH16: (A) Monto de las rentas exenta y deducciones limitadas - 40% | AJ16: =AJ15*0.4 -> 238776800
C17: Ingresos no constitutivos de renta | G17: 33 | H17: ='R.trabajo y honorarios'!H21 -> 14400000 | L17: 44 | M17: ='R.trabajo y honorarios'!L21 -> 22300000 | R17: 59 | S17: ='R.capital'!G37 -> 15112000 | Y17: 76 | Z17: ='R.no laboral y R gravables'!G24 -> 233000000 | AH17: (B) Maximo 1.340 UVT | AJ17: =ROUND('R.trabajo y honorarios'!H74*1340,-3) -> 66731000
C18: Costos y deducciones procedentes | L18: 45 | M18: ='R.trabajo y honorarios'!L34 -> 83000000 | R18: 60 | S18: ='R.capital'!G45 -> 20000000 | Y18: 77 | Z18: ='R.no laboral y R gravables'!G38 -> 64000000 | AH18: (menor entre A y B) Rentas exentas y deducciones limitadas | AJ18: =MIN(AJ17,AJ16) -> 66731000
C19: Renta líquida | G19: 34 | H19: =IF(H15-H17-G18>0,H15-H17-G18,0) -> 245933000 | L19: 46 | M19: =IF(M15-M17-M18>0,M15-M17-M18,0) -> 84700000 | R19: 61 | S19: =IF(S15-S17-S18>0,S15-S17-S18,0) -> 74309000 | Y19: 78 | Z19: =IF(Z15-Z17-Z18-Z16>0,Z15-Z17-Z18-Z16,0) -> 25000000 | AH19: (+) Renta exentas no limitadas | AJ19: =AJ14 -> 0
C20: Rentas líquidas pasivas - ECE | R20: 62 | S20: ='R.capital'!G59 -> 0 | Y20: 79 | Z20: ='R.no laboral y R gravables'!G58 -> 0 | AH20: (=) Rentas exentas y deducciones limitadas definitivas | AJ20: =SUM(AJ18:AJ19) -> 66731000 | AK20: total
C21: Rentas exentas | D21: Aportes voluntarios AFC, FVP y/o AVC | G21: 35 | H21: =ROUND('R.trabajo y honorarios'!G50,-3) -> 22000000 | L21: 47 | M21: ='R.trabajo y honorarios'!K50 -> 0 | R21: 63 | S21: =ROUND('R.capital'!F53,-3) -> 0 | Y21: 80 | Z21: =ROUND('R.no laboral y R gravables'!F64,-3) -> 0 | AH21: Rentas exentas y deducciones - Rentas de trabajo | AJ21: =H26+H23 -> 112609000
D22: Otras rentas exentas | G22: 36 | H22: =ROUND(SUM('R.trabajo y honorarios'!G52:G62),-3) -> 59675000 | L22: 48 | M22: 0 | R22: 64 | S22: 0 | Y22: 81 | Z22: =ROUND('R.no laboral y R gravables'!F66+'R.no laboral y R gravables'!F67+'R.no laboral y R gravables'!F68,-3) -> 0 | AH22: Rentas exentas y deducciones - Rentas de trabajo (limitadas) | AJ22: =MIN(AJ21,AJ20) -> 66731000
D23: Total rentas exentas | G23: 37 | H23: =(H21+H22) -> 81675000 | L23: 49 | M23: =M21+M22 -> 0 | R23: 65 | S23: =S21+S22 -> 0 | Y23: 82 | Z23: =Z21+Z22 -> 0 | AH23: Rentas exentas por distribuir | AJ23: =AJ20-AJ22 -> 0 | AQ23: r. trabajo | AR23: =H15 -> 260333000
C24: Deducciones imputables | D24: Intereses de vivienda | G24: 38 | H24: =ROUND('R.trabajo y honorarios'!G63,-3) -> 0 | L24: 50 | M24: =ROUND('R.trabajo y honorarios'!K63,-3) -> 18000000 | R24: 66 | S24: =ROUND('R.capital'!F55,-3) -> 0 | Y24: 83 | Z24: =ROUND('R.no laboral y R gravables'!F69,-3) -> 0 | AH24: Rentas exentas y deducciones - Honorarios | AJ24: =M23+M26 -> 18000000 | AQ24: r. capital | AR24: =S15 -> 109421000
D25: Otras deducciones imputables | G25: 39 | H25: =ROUND('R.trabajo y honorarios'!G64+'R.trabajo y honorarios'!G65+'R.trabajo y honorarios'!G66+'R.trabajo y honorarios'!G67,-3) -> 30934000 | L25: 51 | M25: =ROUND('R.trabajo y honorarios'!K64+'R.trabajo y honorarios'!K65+'R.trabajo y honorarios'!K66+'R.trabajo y honorarios'!K67,-3) -> 0 | R25: 67 | S25: =ROUND('R.capital'!F56+'R.capital'!F57,-3) -> 0 | Y25: 84 | Z25: =ROUND(('R.no laboral y R gravables'!F70+'R.no laboral y R gravables'!F71),-3) -> 0 | AH25: Rentas exentas y deducciones - Honorarios (limitadas) | AJ25: =MIN(AJ24,AJ23) -> 0 | AQ25: r. no laboral | AR25: =Z15 -> 322000000
D26: Total deducciones imputables | G26: 40 | H26: =SUM(H24:K25) -> 30934000 | L26: 52 | M26: =ROUND(M24+M25,-3) -> 18000000 | R26: 68 | S26: =S24+S25 -> 0 | Y26: 85 | Z26: =Z24+Z25 -> 0 | AH26: Rentas exentas por distribuir | AJ26: =AJ23-AJ25 -> 0 | AQ26: C. dividendos | AR26: =J39+J42+J43 -> 152000000
C27: Rentas exentas y/o deducciones imputables (limitadas) | G27: 41 | H27: =AJ22 -> 66731000 | L27: 53 | M27: =AJ25 -> 0 | R27: 69 | S27: =AJ28 -> 0 | Y27: 86 | Z27: =AJ31 -> 0 | AH27: Rentas exentas y deducciones - Rentas de capital | AJ27: =S23+S26 -> 0 | AQ27: g. ocasional | AR27: =J47 -> 450000000
C28: Renta líquida ordinaria del ejercicio | L28: 54 | M28: =IF(M15-M17-M18-M27>0,M15-M17-M18-M27,0) -> 84700000 | R28: 70 | S28: =IF(S15+S20-S17-S18-S27>0,S15+S20-S17-S18-S27,0) -> 74309000 | Y28: 87 | Z28: =IF(Z15+Z20-Z16-Z17-Z18-Z27>0,Z15+Z20-Z16-Z17-Z18-Z27,0) -> 25000000 | AH28: Rentas exentas y deducciones - Rentas de capital (limitadas) | AJ28: =ROUND(IF(AJ23>AJ27,AJ27,AJ23),-3) -> 0 | AQ28: total | AR28: =SUM(AR23:AR27) -> 1293754000
C29: Pérdida líquida del ejercicio | L29: 55 | M29: =-IF(M15-M17-M18-M27<0,M15-M17-M18-M27,0) -> 0 | R29: 71 | S29: =-IF(S15+S20-S17-S18-S27<0,S15+S20-S17-S18-S27,0) -> 0 | Y29: 88 | Z29: =-IF(Z15+Z20-Z17-Z18-Z27<0,Z15+Z20-Z17-Z18-Z27,0) -> 0 | AH29: Rentas exentas por distribuir | AJ29: =AJ26-AJ28 -> 0
C30: Compensaciones por pérdidas | L30: 56 | M30: =ROUND('R.trabajo y honorarios'!L71,-3) -> 0 | R30: 72 | S30: =ROUND('R.capital'!G66,-3) -> 0 | Y30: 89 | Z30: =ROUND('R.no laboral y R gravables'!G80,-3) -> 0 | AH30: Rentas exentas y deducciones - Rentas no laborales | AJ30: =Z23+Z26 -> 0 | AQ30: R capital y no labo | AR30: =AR25+AR24 -> 431421000
C31: Renta líquida ordinaria | G31: 42 | H31: =H19-H27 -> 179202000 | L31: 57 | M31: =M28-M30 -> 84700000 | R31: 73 | S31: =S28-S30 -> 74309000 | Y31: 90 | Z31: =Z28-Z30 -> 25000000 | AH31: Rentas exentas y deducciones - Rentas no laborales (limitadas) | AJ31: =ROUND(IF(AJ29>AJ30,AJ30,AJ29),-3) -> 0
C32: Ren. líquida céd. gen. | E32: 91 | F32: =ROUND((H27+H31+M27+M31+S27+S31+Z27+Z31),-3) -> 429942000 | I32: Ren. ex. y ded. Imp. Li. | K32: 92 | L32: =H27+M27+S27+Z27+AB12+M52 -> 75308000 | P32: R. liq. ord. cédula gen. | R32: 93 | S32: =F32-L32 -> 354634000 | W32: Comp. Pérdidas año 2018 y ant. | Z32: 94 | AA32: =+M30+S30+Z30 -> 0
C33: Comp. por exc. renta presuntiva | E33: 95 | F33: 0 | I33: Rentas gravables | K33: 96 | L33: =+'R.no laboral y R gravables'!G83 -> 0 | P33: R. liq. grav. cédula gen. | R33: 97 | S33: =S32+L33-AA32-F33 -> 354634000 | W33: Renta presuntiva | Z33: 98 | AA33: ='renta presunt'!E17 -> 0
B34: Cédula de pensiones | C34: Ingresos brutos por rentas de pensiones del país y del exterior | I34: 99 | J34: ='C.pensiones'!F2 -> 0 | P34: Liquidación privada | Q34: Impuesto sobre las rentas líquidas gravables | R34: Cédula general, de pensiones y de dividendos y participaciones | X34: 116 | Y34: =IF('impto renta'!E17>'impto renta'!E18,'impto renta'!E17,0) -> 116647000
C35: Ingresos no constitutivos de renta | I35: 100 | J35: ='C.pensiones'!F18 -> 0 | R35: Renta presuntiva, de pensiones y de dividendos y participaciones | X35: 117 | Y35: =IF('impto renta'!E18>'impto renta'!E17,'impto renta'!E18,0) -> 0
C36: Renta líquida | I36: 101 | J36: =J34-J35 -> 0 | R36: Por dividendos y partipaciones año 2017 y siguientes, 1a. subcédula | X36: 118 | Y36: ='impto renta'!E51 -> 15050000
C37: Rentas exentas de pensiones | I37: 102 | J37: ='C.pensiones'!F26 -> 0 | R37: Por dividendos y partipaciones año 2016 | X37: 119 | Y37: ='impto renta'!E26 -> 0
C38: Renta líquida gravable cédula de pensiones | I38: 103 | J38: =J36-J37 -> 0 | R38: Por dividendos y partipaciones recibidas del exterior | X38: 120 | Y38: ='impto renta'!F47 -> 0
B39: Cédula de dividendos y participaciones | C39: Dividendos y participaciones 2016 y anteriores y otros | I39: 104 | J39: ='C divid.'!F3 -> 59000000 | R39: Total impuestos sobre las rentas líquidas gravables | X39: 121 | Y39: =SUM(Y34:AB38) -> 131697000
C40: Ingresos no constitutivos de renta | I40: 105 | J40: ='C divid.'!F11 -> 34000000 | Q40: Descuentos tributarios | R40: Imp. Pagados en el exterior | T40: 122 | U40: ='dtos tribut'!E2 -> 0 | X40: Donaciones | AA40: 123 | AB40: ='dtos tribut'!E6 -> 10000000
C41: Renta líquida ordinaria año 2016 y anteriores | I41: 106 | J41: =J39-J40 -> 25000000 | R41: Dividendos, partic y otros | T41: 124 | U41: =IF('dtos tribut'!E15>0,'dtos tribut'!E15,0) -> 5063000 | X41: Total des- cuentos trib. | AA41: 125 | AB41: =U40+U41+AB40 -> 15063000
C42: 1a. Subcédula año 2017 y siguientes numeral 3 art. 49 del E.T. | I42: 107 | J42: ='C divid.'!F17 -> 50000000 | Q42: Impuesto neto de renta | X42: 126 | Y42: =Y39-AB41 -> 116634000
C43: 2a. Subcédula año 2017 y siguientes parágrafo 2 art. 49 del E.T. | I43: 108 | J43: ='C divid.'!F25 -> 43000000 | Q43: Impuesto de ganancias ocasionales | X43: 127 | Y43: =+G.OCAS!D101 -> 0
C44: Dividendos y participaciones recibidas del exterior | I44: 109 | J44: ='C divid.'!F33 -> 0 | Q44: Descuento por impuestos pagados en el exterior por ganancias ocasionales | X44: 128 | Y44: ='dtos tribut'!E20 -> 0
C45: Rentas exentas de la casilla 109 | I45: 110 | J45: ='C divid.'!F41 -> 0 | Q45: Total impuesto a cargo | X45: 129 | Y45: =Y42+Y43-Y44 -> 116634000
B46: Renta liquida gravable (Cédula general o renta presuntiva, de pensiones y de dividendos y participaciones, art.241 E.T.) | I46: 111 | J46: =S33+J38+J42+J43-Y36 -> 432584000 | Q46: Anticipo renta liquidado año gravable anterior | X46: 130 | Y46: =anticipo!E4 -> 8700000
B47: Ganancias ocasionales | C47: Ingresos por ganancias ocasionales en el país y del exterior | I47: 112 | J47: =G.OCAS!D94+G.OCAS!D98 -> 450000000 | Q47: Saldo a favor del año gravable anterior sin solicitud de devolución y/o compensación | X47: 131 | Y47: =anticipo!E3 -> 0
C48: Costos por ganancias ocasionales | I48: 113 | J48: =G.OCAS!D95 -> 450000000 | Q48: Retenciones año gravable a declarar | X48: 132 | Y48: =retefuente!E3 -> 20820000
C49: Ganancias ocasionales no gravadas y exentas | I49: 114 | J49: =G.OCAS!D96 -> 0 | Q49: Anticipo renta para el año gravable siguiente | X49: 133 | Y49: =anticipo!E40 -> 29668000
C50: Ganancias ocasionales gravables | I50: 115 | J50: =J47-J48-J49 -> 0
B51: Saldo a pagar por impuesto | E51: 134 | F51: =IF(Y45+Y49-Y46-Y47-Y48>0,Y45+Y49-Y46-Y47-Y48,0) -> 116782000 | I51: Sanciones | L51: 135 | M51: 0 | P51: Total Saldo a pagar | T51: 136 | U51: =F51+M51 -> 116782000 | X51: Total saldo a favor | AA51: 137 | AB51: =-IF(Y45+Y49+M51-Y46-Y47-Y48<0,Y45+Y49+M51-Y46-Y47-Y48,0) -> 0
B52: Número de dependientes economicos | E52: 138 | F52: ='Dependientes '!C3 -> 2 | I52: Adición por dependientes a la casilla 92 | L52: 139 | M52: ='Dependientes '!C11 -> 6777000 | P52: Ud. Superó tope indicativo art.336-1 del ET, marque X | T52: 140 | X52: Aporte voluntario | AA52: 141

Sheet rta x comp patr
B1: Renta Líquida por Comparación Patrimonial
B2: Procedimiento para su Determinación
B3: Concepto | C3: Valores
B4: Patrimonio líquido del año gravable corriente | C4: ='FORMULARIO 210'!Z13 -> 4130790000
A5: ( + ) | B5: Desvalorizaciones | C5: 0
A6: ( - ) | B6: Valorizaciones | C6: ='Pat bruto'!H119 -> 448450000
A7: ( - ) | B7: Patrimonio líquido del año gravable anterior | C7: ='renta presunt'!E6 -> 3070000000
A8: ( = ) | B8: Variación por comparación patrimonial | C8: =IF(C4+C5-C6-C7>0,C4+C5-C6-C7,0) -> 612340000
B9: Posteriormente
B10: Ajuste de las Rentas
B11: Valor de las Rentas líquidas Cedulares antes de compensaciones | C11: ='FORMULARIO 210'!S32+'FORMULARIO 210'!J38+'FORMULARIO 210'!J41+'FORMULARIO 210'!J42+'FORMULARIO 210'!J43+'FORMULARIO 210'!J44 -> 472634000
A12: ( + ) | B12: Rentas exentas (sin límite) y ganancias ocasionales exentas y no gravadas | C12: ='FORMULARIO 210'!H23+'FORMULARIO 210'!M23+'FORMULARIO 210'!S23+'FORMULARIO 210'!Z23+'FORMULARIO 210'!J37+'FORMULARIO 210'!J45+'FORMULARIO 210'!J50 -> 81675000
A13: ( + ) | B13: Ingresos no constitutivos de renta ni ganancia ocasional | C13: ='FORMULARIO 210'!H17+'FORMULARIO 210'!M17+'FORMULARIO 210'!S17+'FORMULARIO 210'!Z17+'FORMULARIO 210'!J35+'FORMULARIO 210'!J40 -> 318812000
A14: ( + ) | B14: Ganancias ocasionales netas (ingreso por ganancia ocasional - costos por ganancia ocasional) | C14: 0
A15: ( - ) | B15: Impuestos y anticipos pagados en el año gravable | C15: 45000000
A16: ( - ) | B16: Retenciones en la fuente practicadas en el año gravable | C16: ='FORMULARIO 210'!Y48 -> 20820000
A17: ( = ) | B17: Valor de las rentas ajustadas | C17: =((C11+'rta x comp patr'!C12+C13+C14)-(C15+C16)) -> 807301000
B18: Resultado
B19: Variación por comparacion patrimonial | C19: =+C8 -> 612340000
B20: Valor rentas ajustadas | C20: =IF(OR(C11<0,ISTEXT(C11),'rta x comp patr'!C12<0,ISTEXT('rta x comp patr'!C12),C13<0,ISTEXT(C13),C14<0,ISTEXT(C14),C15<0,ISTEXT(C15),C16<0,ISTEXT(C16)), "Por favor ingrese valores positivos en la celdas B18 a B23.",C11+'rta x comp patr'!C12+C13+C14-C15-C16) -> 807301000
B21: Incremento patrimonial no justificado | C21: =IF(C19>C20,C19-C20,0) -> 0
B22: =IF(C20>C19,B27,IF(C20<C19,B29,IF(C20=C19,B25,0))) -> Esta situación también es buena para el contribuyente ya que la Autoridad Fiscal no cuestiona el porque no se invirtieron todos los ingresos en activos para incrementar el patrimonio líquido. No hay renta por comparación patrimonial
B24: Variación patrimonial = Rentas ajustadas
B25: Esta es la situación ideal, ya que se ve reflejado de manera clara los ingresos con los cuales fue posible comprar bienes y derechos que incrementaron el patrimonio líquido. No hay renta por comparación patrimonial
B26: Variación patrimonial < Rentas ajustadas
B27: Esta situación también es buena para el contribuyente ya que la Autoridad Fiscal no cuestiona el porque no se invirtieron todos los ingresos en activos para incrementar el patrimonio líquido. No hay renta por comparación patrimonial
B28: Variación patrimonial > Rentas ajustadas
B29: A esta situación es que la DIAN le prestará especial atención, ya que en el orden de las cosas, se necesitan ingresos para poder comprar bienes o derechos. Al ser las rentas ajustadas inferiores a la variación presentada en el patrimonio, no existe a primera vista, una justificación del incremento. Hay renta por comparación patrimonial

Sheet Hoja1
F4: Año de adquisición | G4: Acciones y Aportes | H4: Bienes Raíces
F5: Multiplicar por
F6: 1955 y anteriores | G6: 3581.32 | H6: 32137.12
F7: 1956 | G7: 3509.63 | H7: 31494.78
F8: 1957 | G8: 3249.68 | H8: 29162.19
F9: 1958 | G9: 2741.82 | H9: 24604.31
F10: 1959 | G10: 2506.66 | H10: 22494.25
F11: 1960 | G11: 2339.61 | H11: 20994.94
F12: 1961 | G12: 2193.32 | H12: 19576.13
F13: 1962 | G13: 2064.46 | H13: 18525.04
F14: 1963 | G14: 1928.23 | H14: 17303.51
F15: 1964 | G15: 1474.42 | H15: 13231.72
F16: 1965 | G16: 1349.81 | H16: 12112.77
F17: 1966 | G17: 1177.62 | H17: 10567.7
F18: 1967 | G18: 1038.26 | H18: 9317.76
... F72: 2021 | G72: 1.06 | H72: 1.03

Sheet Pat bruto
B2: PATRIMONIO BRUTO (Renglón 29)
B4: ENTIDADES FINANCiERAS, FONDOS CESANTIAS, ETC | D4: SALDO 31 DE DICIEMBRE
B6: Banco Davivienda | D6: 345980000
B7: Saldo aportes voluntarios a fondo de pensiones voluntarios porvenir | D7: 255000000
B8: CDT Banco Davivienda | D8: =290000000+8000000 -> 298000000
B9: Banco Caja social cta ahorros | D9: 135000000
B29: TOTAL ENTIDADES FINANCIERAS Y CESANTÍAS | D29: =SUM(D5:D28) -> 1033980000
B32: CUENTAS POR COBRAR, INVENTARIOS: | D32: SALDO 31 DE DICIEMBRE
B35: Cesar Anzola | D35: 12000000
B58: CUENTAS POR COBRAR | D58: =SUM(D33:D57) -> 12000000
B61: ACCIONES, APORTES EN SOCIDADES
B62: Descripción | C62: Reajuste fiscal | D62: Costo fiscal a Dic. 31 de 2024 | E62: Costo de compra en el año 2025 | F62: Reajuste fiscal 2025 5,81% Dec. 0049/2026 | G62: Valor patrimonial a Dic. 31 de 2025 | H62: Valorización año 2025
F63: =IF(C63>"No",D63*$D$121,0) -> 0 | G63: =SUM(D63:F63) -> 0 | H63: =G63-E63-D63 -> 0
B64: Acciones en ITGS SAS Cantidad 7.670 vr nomial $8.000 | C64: No | D64: =8000*7670 -> 61360000 | F64: =IF(C64>"No",D64*$D$121,0) -> 0 | G64: =SUM(D64:F64) -> 61360000 | H64: =G64-E64-D64 -> 0
B65: Acciones Banco Davivienda | C65: No | E65: 870000000 | F65: =IF(C65>"No",D65*$D$121,0) -> 0 | G65: =SUM(D65:F65) -> 870000000 | H65: =G65-E65-D65 -> 0
C66: No | F66: =IF(C66>"No",D66*$D$121,0) -> 0 | G66: =SUM(D66:F66) -> 0 | H66: =G66-E66-D66 -> 0
C67: No | F67: =IF(C67>"No",D67*$D$121,0) -> 0 | G67: =SUM(D67:F67) -> 0 | H67: =G67-E67-D67 -> 0
C68: No | F68: =IF(C68>"No",D68*$D$121,0) -> 0 | G68: =SUM(D68:F68) -> 0 | H68: =G68-E68-D68 -> 0
C69: No | F69: =IF(C69>"No",D69*$D$121,0) -> 0 | G69: =SUM(D69:F69) -> 0 | H69: =G69-E69-D69 -> 0
C70: No | F70: =IF(C70>"No",D70*$D$121,0) -> 0 | G70: =SUM(D70:F70) -> 0 | H70: =G70-E70-D70 -> 0
E71: 0 | F71: =IF(C71>"No",D71*$D$121,0) -> 0 | G71: =SUM(D71:F71) -> 0 | H71: =G71-E71-D71 -> 0
E72: 0 | F72: =IF(C72>"No",D72*$D$121,0) -> 0 | G72: =SUM(D72:F72) -> 0 | H72: =G72-E72-D72 -> 0
F73: =IF(C73>"No",D73*$D$121,0) -> 0 | G73: =SUM(D73:F73) -> 0 | H73: =G73-E73-D73 -> 0
F74: =IF(C74>"No",D74*$D$121,0) -> 0 | G74: =SUM(D74:F74) -> 0 | H74: =G74-E74-D74 -> 0
F75: =IF(C75>"No",D75*$D$121,0) -> 0 | G75: =SUM(D75:F75) -> 0 | H75: =G75-E75-D75 -> 0
F76: =IF(C76>"No",D76*$D$121,0) -> 0 | G76: =SUM(D76:F76) -> 0 | H76: =G76-E76-D76 -> 0
F77: =IF(C77>"No",D77*$D$121,0) -> 0 | G77: =SUM(D77:F77) -> 0 | H77: =G77-E77-D77 -> 0
F78: =IF(C78>"No",D78*$D$121,0) -> 0 | G78: =SUM(D78:F78) -> 0 | H78: =G78-E78-D78 -> 0
B79: Valor Patrimonial a Diciembre 31 de 2024 y Valorización | G79: =SUM(G63:G78) -> 931360000 | H79: =SUM(H63:H78) -> 0
B82: ACTIVOS FIJOS Y OTROS ACTIVOS - OPCIÓN 1
B83: Descripción | C83: Reajuste fiscal | D83: Costo fiscal a Dic. 31 de 2024 | E83: Costo de compra (y/o mejoras, val. pagadas) del 2025 | F83: Reajuste fiscal 2025 5,81% Dec. 0049/2026 | G83: Costo fiscal a Dic. 31 de 2025 | H83: Avaluo Catastral o Auto avaluo catastral 2025 | I83: Valor patrimonial a Dic. 31 de 2025 | J83: Valorización año 2025
C84: No | D84: 0 | F84: =IF(C84>"No",D84*$D$121,0) -> 0 | G84: =SUM(D84:F84) -> 0 | I84: =IF(H84>G84,H84,G84) -> 0 | J84: =I84-E84-D84 -> 0
B85: Vehiculo nissa xtrail modelo 2023 | C85: No | D85: 230000000 | F85: =IF(C85>"No",D85*$D$121,0) -> 0 | G85: =SUM(D85:F85) -> 230000000 | I85: =IF(H85>G85,H85,G85) -> 230000000 | J85: =I85-E85-D85 -> 0
B86: Apto calle 19 cra 3 | C86: No | D86: 643000000 | E86: 12000000 | F86: =IF(C86>"No",D86*$D$121,0) -> 0 | G86: =SUM(D86:F86) -> 655000000 | H86: 670000000 | I86: =IF(H86>G86,H86,G86) -> 670000000 | J86: =I86-E86-D86 -> 15000000
B87: Oficina calle 93 cra 15 | C87: No | D87: 780000000 | F87: =IF(C87>"No",D87*$D$121,0) -> 0 | G87: =SUM(D87:F87) -> 780000000 | H87: 815000000 | I87: =IF(H87>G87,H87,G87) -> 815000000 | J87: =I87-E87-D87 -> 35000000
C88: No | F88: =IF(C88>"No",D88*$D$121,0) -> 0 | G88: =SUM(D88:F88) -> 0 | I88: =IF(H88>G88,H88,G88) -> 0 | J88: =I88-E88-D88 -> 0
C89: Si | F89: =IF(C89>"No",D89*$D$121,0) -> 0 | G89: =SUM(D89:F89) -> 0 | I89: =IF(H89>G89,H89,G89) -> 0 | J89: =I89-E89-D89 -> 0
C90: Si | F90: =IF(C90>"No",D90*$D$121,0) -> 0 | G90: =SUM(D90:F90) -> 0 | I90: =IF(H90>G90,H90,G90) -> 0 | J90: =I90-E90-D90 -> 0
C91: No | F91: =IF(C91>"No",D91*$D$121,0) -> 0 | G91: =SUM(D91:F91) -> 0 | I91: =IF(H91>G91,H91,G91) -> 0 | J91: =I91-E91-D91 -> 0
C92: No | D92: 0 | F92: =IF(C92>"No",D92*$D$121,0) -> 0 | G92: =SUM(D92:F92) -> 0 | I92: =IF(H92>G92,H92,G92) -> 0 | J92: =I92-E92-D92 -> 0
C93: No | D93: 0 | F93: =IF(C93>"No",D93*$D$121,0) -> 0 | G93: =SUM(D93:F93) -> 0 | I93: =IF(H93>G93,H93,G93) -> 0 | J93: =I93-E93-D93 -> 0
C94: No | D94: 0 | F94: =IF(C94>"No",D94*$D$121,0) -> 0 | G94: =SUM(D94:F94) -> 0 | I94: =IF(H94>G94,H94,G94) -> 0 | J94: =I94-E94-D94 -> 0
C95: No | D95: 0 | E95: 0 | F95: =IF(C95>"No",D95*$D$121,0) -> 0 | G95: =SUM(D95:F95) -> 0 | I95: =IF(H95>G95,H95,G95) -> 0 | J95: =I95-E95-D95 -> 0
C96: No | D96: 0 | F96: =IF(C96>"No",D96*$D$121,0) -> 0 | G96: =SUM(D96:F96) -> 0 | I96: =IF(H96>G96,H96,G96) -> 0 | J96: =I96-E96-D96 -> 0
C97: Si | E97: 0 | F97: =IF(C97>"No",D97*$D$121,0) -> 0 | G97: =SUM(D97:F97) -> 0 | I97: =IF(H97>G97,H97,G97) -> 0 | J97: =I97-E97-D97 -> 0
C98: Si | E98: 0 | F98: =IF(C98>"No",D98*$D$121,0) -> 0 | G98: =SUM(D98:F98) -> 0 | I98: =IF(H98>G98,H98,G98) -> 0 | J98: =I98-E98-D98 -> 0
C99: Si | F99: =IF(C99>"No",D99*$D$121,0) -> 0 | G99: =SUM(D99:F99) -> 0 | I99: =IF(H99>G99,H99,G99) -> 0 | J99: =I99-E99-D99 -> 0
C100: Si | F100: =IF(C100>"No",D100*$D$121,0) -> 0 | G100: =SUM(D100:F100) -> 0 | I100: =IF(H100>G100,H100,G100) -> 0 | J100: =I100-E100-D100 -> 0
B101: Valor Patrimonial a Diciembre 31 de 2024 y Valorización | I101: =SUM(I84:I100) -> 1715000000 | J101: =SUM(J84:J100) -> 50000000
B104: ACTIVOS FIJOS Y ACCIONES OPCIÓN 2 ART. 73 E.T.
B105: Descripción | C105: Costo fiscal a Dic. 31 de 2024 | D105: Costo original de adquisición | E105: BIENES RAICES O ACCIONES | F105: FECHA DE ADQUISICIÓN | G105: Factor según tabla art. 73 E.T. (Art. 1 Dec. 0049 2026) | H105: Total costo fiscal Dic. 31 de 2025 | I105: Valorización año 2025
B106: Apto cra 22 No. 45-34 torre 4 apto 624 | C106: 450000000 | D106: 355000000 | E106: BIENES URBANOS | F106: 2012 | G106: =IF('Pat bruto'!E106="ACCIONES",VLOOKUP('Pat bruto'!F106,Sheet1!$B$5:$F$75,2),IF('Pat bruto'!E106="BIENES URBANOS",VLOOKUP('Pat bruto'!F106,Sheet1!$B$5:$F$75,3),IF('Pat bruto'!E106="BIENES RURALES",VLOOKUP('Pat bruto'!F106,Sheet1!$B$5:$F$75,5),IF('Pat bruto'!E106="Bienes Raíces Rurales dedicados a actividades agropecuarias",VLOOKUP('Pat bruto'!F106,Sheet1!$B$5:$F$75,4),0)))) -> 2.39 | H106: =D106*'Pat bruto'!G106 -> 848450000 | I106: =+H106-C106 -> 398450000
G107: =IF('Pat bruto'!E107="ACCIONES",VLOOKUP('Pat bruto'!F107,Sheet1!$B$5:$F$75,2),IF('Pat bruto'!E107="BIENES URBANOS",VLOOKUP('Pat bruto'!F107,Sheet1!$B$5:$F$75,3),IF('Pat bruto'!E107="BIENES RURALES",VLOOKUP('Pat bruto'!F107,Sheet1!$B$5:$F$75,5),IF('Pat bruto'!E107="Bienes Raíces Rurales dedicados a actividades agropecuarias",VLOOKUP('Pat bruto'!F107,Sheet1!$B$5:$F$75,4),0)))) -> 0 | H107: =D107*G107 -> 0 | I107: =+H107-C107 -> 0
G108: =IF('Pat bruto'!E108="ACCIONES",VLOOKUP('Pat bruto'!F108,Sheet1!$B$5:$F$75,2),IF('Pat bruto'!E108="BIENES URBANOS",VLOOKUP('Pat bruto'!F108,Sheet1!$B$5:$F$75,3),IF('Pat bruto'!E108="BIENES RURALES",VLOOKUP('Pat bruto'!F108,Sheet1!$B$5:$F$75,5),IF('Pat bruto'!E108="Bienes Raíces Rurales dedicados a actividades agropecuarias",VLOOKUP('Pat bruto'!F108,Sheet1!$B$5:$F$75,4),0)))) -> 0 | H108: =D108*G108 -> 0 | I108: =+H108-C108 -> 0
G109: =IF('Pat bruto'!E109="ACCIONES",VLOOKUP('Pat bruto'!F109,Sheet1!$B$5:$F$75,2),IF('Pat bruto'!E109="BIENES URBANOS",VLOOKUP('Pat bruto'!F109,Sheet1!$B$5:$F$75,3),IF('Pat bruto'!E109="BIENES RURALES",VLOOKUP('Pat bruto'!F109,Sheet1!$B$5:$F$75,5),IF('Pat bruto'!E109="Bienes Raíces Rurales dedicados a actividades agropecuarias",VLOOKUP('Pat bruto'!F109,Sheet1!$B$5:$F$75,4),0)))) -> 0 | H109: =D109*G109 -> 0 | I109: =+H109-C109 -> 0
G110: =IF('Pat bruto'!E110="ACCIONES",VLOOKUP('Pat bruto'!F110,Sheet1!$B$5:$F$75,2),IF('Pat bruto'!E110="BIENES URBANOS",VLOOKUP('Pat bruto'!F110,Sheet1!$B$5:$F$75,3),IF('Pat bruto'!E110="BIENES RURALES",VLOOKUP('Pat bruto'!F110,Sheet1!$B$5:$F$75,5),IF('Pat bruto'!E110="Bienes Raíces Rurales dedicados a actividades agropecuarias",VLOOKUP('Pat bruto'!F110,Sheet1!$B$5:$F$75,4),0)))) -> 0 | H110: =D110*G110 -> 0 | I110: =+H110-C110 -> 0
G111: =IF('Pat bruto'!E111="ACCIONES",VLOOKUP('Pat bruto'!F111,Sheet1!$B$5:$F$75,2),IF('Pat bruto'!E111="BIENES URBANOS",VLOOKUP('Pat bruto'!F111,Sheet1!$B$5:$F$75,3),IF('Pat bruto'!E111="BIENES RURALES",VLOOKUP('Pat bruto'!F111,Sheet1!$B$5:$F$75,5),IF('Pat bruto'!E111="Bienes Raíces Rurales dedicados a actividades agropecuarias",VLOOKUP('Pat bruto'!F111,Sheet1!$B$5:$F$75,4),0)))) -> 0 | H111: =D111*G111 -> 0 | I111: =+H111-C111 -> 0
G112: =IF('Pat bruto'!E112="ACCIONES",VLOOKUP('Pat bruto'!F112,Sheet1!$B$5:$F$75,2),IF('Pat bruto'!E112="BIENES URBANOS",VLOOKUP('Pat bruto'!F112,Sheet1!$B$5:$F$75,3),IF('Pat bruto'!E112="BIENES RURALES",VLOOKUP('Pat bruto'!F112,Sheet1!$B$5:$F$75,5),IF('Pat bruto'!E112="Bienes Raíces Rurales dedicados a actividades agropecuarias",VLOOKUP('Pat bruto'!F112,Sheet1!$B$5:$F$75,4),0)))) -> 0 | H112: =D112*G112 -> 0 | I112: =+H112-C112 -> 0
G113: =IF('Pat bruto'!E113="ACCIONES",VLOOKUP('Pat bruto'!F113,Sheet1!$B$5:$F$75,2),IF('Pat bruto'!E113="BIENES URBANOS",VLOOKUP('Pat bruto'!F113,Sheet1!$B$5:$F$75,3),IF('Pat bruto'!E113="BIENES RURALES",VLOOKUP('Pat bruto'!F113,Sheet1!$B$5:$F$75,5),IF('Pat bruto'!E113="Bienes Raíces Rurales dedicados a actividades agropecuarias",VLOOKUP('Pat bruto'!F113,Sheet1!$B$5:$F$75,4),0)))) -> 0 | H113: =D113*G113 -> 0 | I113: =+H113-C113 -> 0
G114: =IF('Pat bruto'!E114="ACCIONES",VLOOKUP('Pat bruto'!F114,Sheet1!$B$5:$F$75,2),IF('Pat bruto'!E114="BIENES URBANOS",VLOOKUP('Pat bruto'!F114,Sheet1!$B$5:$F$75,3),IF('Pat bruto'!E114="BIENES RURALES",VLOOKUP('Pat bruto'!F114,Sheet1!$B$5:$F$75,5),IF('Pat bruto'!E114="Bienes Raíces Rurales dedicados a actividades agropecuarias",VLOOKUP('Pat bruto'!F114,Sheet1!$B$5:$F$75,4),0)))) -> 0 | H114: =D114*G114 -> 0 | I114: =+H114-C114 -> 0
G115: =IF('Pat bruto'!E115="ACCIONES",VLOOKUP('Pat bruto'!F115,Sheet1!$B$5:$F$75,2),IF('Pat bruto'!E115="BIENES URBANOS",VLOOKUP('Pat bruto'!F115,Sheet1!$B$5:$F$75,3),IF('Pat bruto'!E115="BIENES RURALES",VLOOKUP('Pat bruto'!F115,Sheet1!$B$5:$F$75,5),IF('Pat bruto'!E115="Bienes Raíces Rurales dedicados a actividades agropecuarias",VLOOKUP('Pat bruto'!F115,Sheet1!$B$5:$F$75,4),0)))) -> 0 | H115: =D115*G115 -> 0 | I115: =+H115-C115 -> 0
G116: =IF('Pat bruto'!E116="ACCIONES",VLOOKUP('Pat bruto'!F116,Sheet1!$B$5:$F$75,2),IF('Pat bruto'!E116="BIENES URBANOS",VLOOKUP('Pat bruto'!F116,Sheet1!$B$5:$F$75,3),IF('Pat bruto'!E116="BIENES RURALES",VLOOKUP('Pat bruto'!F116,Sheet1!$B$5:$F$75,5),IF('Pat bruto'!E116="Bienes Raíces Rurales dedicados a actividades agropecuarias",VLOOKUP('Pat bruto'!F116,Sheet1!$B$5:$F$75,4),0)))) -> 0 | H116: =D116*G116 -> 0 | I116: =+H116-C116 -> 0
B117: Valor Patrimonial a Diciembre 31 de 2024 y Valorización | H117: =SUM(H106:H116) -> 848450000 | I117: =SUM(I106:I116) -> 398450000
B119: Total Patrimonio Bruto y Total valorizaciones | G119: =ROUND((H117+I101+G79+D58+D29),-3) -> 4540790000 | H119: =(I117+J101+H79) -> 448450000
B121: % de Reajuste Fiscal | D121: 0.0581

Sheet EXOGENA 2025

Sheet Sheet1
E2: UVT | F2: ='R.trabajo y honorarios'!H74 -> 49799
C3: =#REF! -> #REF!
B5: Año | C5: Acciones y aportes | D5: Bienes urbanos | E5: Bienes Raíces Rurales dedicados a actividades agropecuarias | F5: Bienes Rurales | I5: =42412*L7 -> 14844200 | R5: Aportes voluntarios - Renta de trabajo | U5: exentas al 25%
B6: 1955 y anteriores | C6: 4664.64 | D6: 36085.1 | E6: 34963.67 | F6: 35631.92 | H6: Renta de trabajo - censantias y intereses | R6: Limite 3.800 UVT | S6: ='R.trabajo y honorarios'!H74*3800 -> 189236200 | U6: =240*12 -> 2880
B7: 1956 | C7: 4571.26 | D7: 35363.86 | E7: 34264.84 | F7: 34919.74 | H7: Entre | I7: =L7*'R.trabajo y honorarios'!$H$74 -> 17429650 | J7: Y | K7: =O7*'R.trabajo y honorarios'!$H$74 -> 20417590 | L7: 350 | M7: UVT | N7: Y | O7: 410 | P7: 0.9 | R7: Limite ingresos | S7: ='R.trabajo y honorarios'!H4*30% -> 78099900 | U7: =U6*'R.trabajo y honorarios'!H74 -> 143421120
B8: 1957 | C8: 4232.67 | D8: 32744.71 | E8: 31727.09 | F8: 32333.48 | H8: Entre | I8: =L8*'R.trabajo y honorarios'!$H$74 -> 20417590 | J8: Y | K8: =O8*'R.trabajo y honorarios'!$H$74 -> 23405530 | L8: 410 | M8: UVT | N8: Y | O8: 470 | P8: 0.8 | R8: Valor reportado | S8: ='R.trabajo y honorarios'!F50+'R.trabajo y honorarios'!F51 -> 22000000
B9: 1958 | C9: 3571.2 | D9: 27626.91 | E9: 26768.34 | F9: 27279.95 | H9: Entre | I9: =L9*'R.trabajo y honorarios'!$H$74 -> 23405530 | J9: Y | K9: =O9*'R.trabajo y honorarios'!$H$74 -> 26393470 | L9: 470 | M9: UVT | N9: Y | O9: 530 | P9: 0.6 | R9: Valor a reportar | S9: =MIN(S6:S8) -> 22000000
B10: 1959 | C10: 3264.9 | D10: 25257.62 | E10: 24472.68 | F10: 24940.42 | H10: Entre | I10: =L10*'R.trabajo y honorarios'!$H$74 -> 26393470 | J10: Y | K10: =O10*'R.trabajo y honorarios'!$H$74 -> 29381410 | L10: 530 | M10: UVT | N10: Y | O10: 590 | P10: 0.4 | U10: INCRNGO
B11: 1960 | C11: 3047.31 | D11: 23574.13 | E11: 22841.51 | F11: 23278.07 | H11: Entre | I11: =L11*'R.trabajo y honorarios'!$H$74 -> 29381410 | J11: Y | K11: =O11*'R.trabajo y honorarios'!$H$74 -> 32369350 | L11: 590 | M11: UVT | N11: Y | O11: 650 | P11: 0.2 | U11: Aporte voluntario a fondo obligatorio porvenir - RAIS - Renta de trabajo | V11: Aporte voluntario a fondo obligatorio porvenir - RAIS - Honorarios | W11: Aporte voluntario a fondo obligatorio porvenir - RAIS - Renta de capital | X11: Aporte voluntario a fondo obligatorio porvenir - RAIS - Renta no laboral | Y11: ,
B12: 1961 | C12: 2856.78 | D12: 21981.02 | E12: 21297.91 | F12: 21704.97 | H12: De | I12: =L12*'R.trabajo y honorarios'!$H$74 -> 32419149 | J12: a | K12: =O12*'R.trabajo y honorarios'!$H$74 -> 497940201 | L12: 651 | M12: UVT | N12: Y | O12: 9999 | P12: 0 | R12: A restar | S12: =S6-S9 -> 167236200 | T12: Limite ingresos | U12: ='R.trabajo y honorarios'!H4*25% -> 65083250 | V12: ='R.trabajo y honorarios'!L4*25% -> 47500000 | W12: ='R.capital'!G2*25% -> 27355250 | X12: ='R.no laboral y R gravables'!G3*25% -> 80500000
B13: 1962 | C13: 2688.94 | D13: 20800.81 | E13: 20154.38 | F13: 20539.58 | R13: Aportes voluntarios - honorarios | T13: Limite UVT | U13: ='R.trabajo y honorarios'!H74*2500 -> 124497500 | V13: =U13 -> 124497500 | W13: =U13 -> 124497500 | X13: =W13 -> 124497500
B14: 1963 | C14: 2511.5 | D14: 19429.21 | E14: 18825.4 | F14: 19185.21 | I14: Salario mensual | K14: ='R.trabajo y honorarios'!H3 -> 13333333 | R14: Limite 3.800 UVT | S14: =S6 -> 189236200 | T14: Valor reportad | U14: ='R.trabajo y honorarios'!F24 -> 0 | V14: ='R.trabajo y honorarios'!J24 -> 0 | W14: ='R.capital'!E40 -> 0 | X14: ='R.no laboral y R gravables'!E24 -> 0
B15: 1964 | C15: 1920.42 | D15: 14857.22 | E15: 14395.49 | F15: 14670.63 | I15: Cesantias | K15: ='R.trabajo y honorarios'!F52+'R.trabajo y honorarios'!F53+'R.trabajo y honorarios'!F54 -> 20333333 | R15: Limite ingresos | S15: ='R.trabajo y honorarios'!L4*30% -> 57000000 | U15: =MIN(U12,U13,U14) -> 0 | V15: =MIN(V12,V13,V14) -> 0 | W15: =MIN(W12,W13,W14) -> 0 | X15: =MIN(X12,X13,X14) -> 0
B16: 1965 | C16: 1758.11 | D16: 13600.8 | E16: 13178.13 | F16: 13429.99 | K16: =K15*P8 -> 16266667 | R16: Valor reportado | S16: ='R.trabajo y honorarios'!J50+'R.trabajo y honorarios'!J51 -> 0 | T16: A resultar | U16: =U13-U15 -> 124497500
B17: 1966 | C17: 1533.84 | D17: 11865.93 | E17: 11497.16 | F17: 11716.9 | R17: Valor a reportar | S17: =MIN(S14:S16) -> 0 | T17: Condicional 2 | V17: =MIN(U16,V15) -> 0
B18: 1967 | C18: 1352.33 | D18: 10462.43 | E18: 10137.28 | F18: 10331.03 | I18: ='R.trabajo y honorarios'!C52 -> Cesantías consignadas | K18: ='R.trabajo y honorarios'!F52 -> 13333333 | L18: =K18/$K$21 -> 0.6557377 | R18: FINAL DE HONORARIOS | S18: =MIN(S12,S17) -> 0
B19: 1968 | C19: 1255.75 | D19: 9714.61 | E19: 9412.7 | F19: 9592.6 | I19: ='R.trabajo y honorarios'!C53 -> Intereses sobre cesantías | K19: ='R.trabajo y honorarios'!F53 -> 7000000 | L19: =K19/$K$21 -> 0.3442623
B20: 1969 | C20: 1178.09 | D20: 9113.87 | E20: 8830.63 | F20: 8999.41 | I20: ='R.trabajo y honorarios'!C54 -> Retiro de cesantias antes del año 2016 (Ley 1819 del 2016) No limitada | K20: ='R.trabajo y honorarios'!F54 -> 0 | L20: =K20/$K$21 -> 0 | R20: Aportes voluntarios - Renta de capital
B21: 1970 | C21: 1083.26 | D21: 8380.22 | E21: 8119.79 | F21: 8274.98 | I21: TOTAL | K21: =SUM(K18:K20) -> 20333333 | R21: Limite 3.800 UVT | S21: =S14 -> 189236200 | AA21: Ingresos brutos anuales | AC21: Ingresos brutos anuales | AE21: Tarifa marginal | AF21: CALCULO | AG21: BASE CEDULA GENERAL Y PENSIÓN | AH21: IMPUESTO
B22: 1971 | C22: 1011.41 | D22: 7823.78 | E22: 7580.64 | F22: 7725.53 | R22: Limite ingresos | S22: ='R.capital'!G2*30% -> 32826300 | AA22: Igual o superior | AB22: Igual o superior | AC22: Inferior
B23: 1972 | C23: 896.22 | D23: 6934.19 | E23: 6718.7 | F23: 6847.11 | I23: LIMITE | K23: ='R.trabajo y honorarios'!G52 -> 20333333 | R23: Valor reportado | S23: ='R.capital'!E53+'R.capital'!E54 -> 0 | AA23: 0 | AB23: 1090 | AC23: =AA23*Sheet1!$F$2 -> 0 | AD23: =AB23*Sheet1!$F$2 -> 54280910 | AE23: 0 | AF23: 0 | AG23: =#REF! -> #REF! | AH23: 0
B24: 1973 | C24: 788.01 | D24: 6097.77 | E24: 5908.26 | F24: 6021.19 | I24: =I18 -> Cesantías consignadas | K24: =L18*$K$23 -> 13333333 | R24: VALOR A REPORTAR | S24: =MIN(S21:S23) -> 0 | AA24: =AB23+1 -> 1091 | AB24: 1700 | AC24: =AA24*Sheet1!$F$2 -> 54330709 | AD24: =AB24*Sheet1!$F$2 -> 84658300 | AE24: 0.19 | AF24: (Base gravable en UVT Menos 1090 UVT) *19% | AG24: =#REF! -> #REF! | AH24: =(((AG24/Sheet1!$F$2)-1090)*19%)*Sheet1!AE11 -> #REF!
B25: 1974 | C25: 643.73 | D25: 4981.35 | E25: 4826.54 | F25: 4918.79 | I25: =I19 -> Intereses sobre cesantías | K25: =L19*$K$23 -> 7000000 | AA25: =AB24+1 -> 1701 | AB25: 4100 | AC25: =AA25*Sheet1!$F$2 -> 84708099 | AD25: =AB25*Sheet1!$F$2 -> 204175900 | AE25: 0.28 | AF25: (Base gravable en UVT Menos 1700 UVT) *28% + 116 UVT | AG25: =#REF! -> #REF! | AH25: =((((AG25/Sheet1!$F$2)-1700)*28%)+116)*Sheet1!$F$2 -> #REF!
B26: 1975 | C26: 514.87 | D26: 3981.89 | E26: 3858.14 | F26: 3931.88 | I26: =I20 -> Retiro de cesantias antes del año 2016 (Ley 1819 del 2016) No limitada | K26: =L20*$K$23 -> 0 | R26: Aportes voluntarios - No laborales | AA26: =AB25+1 -> 4101 | AB26: 8670 | AC26: =AA26*Sheet1!$F$2 -> 204225699 | AD26: =AB26*Sheet1!$F$2 -> 431757330 | AE26: 0.33 | AF26: (Base gravable en UVT Menos 4100 UVT) *33% + 788 UVT | AG26: =#REF! -> #REF! | AH26: =((((AG26/Sheet1!$F$2)-4100)*33%)+788)*Sheet1!$F$2 -> #REF!
B27: 1976 | C27: 437.78 | D27: 3385.47 | E27: 3281.22 | F27: 3343.94 | R27: Limite 3.800 UVT | S27: =S14 -> 189236200 | AA27: =AB26+1 -> 8671 | AB27: 18970 | AC27: =AA27*Sheet1!$F$2 -> 431807129 | AD27: =AB27*Sheet1!$F$2 -> 944687030 | AE27: 0.35 | AF27: (Base gravable en UVT Menos 8670 UVT) *35% + 2296 UVT | AG27: =#REF! -> #REF! | AH27: =((((AG27/Sheet1!$F$2)-8670)*35%)+2296)*Sheet1!$F$2 -> #REF!
B28: 1977 | C28: 349.06 | D28: 2698.9 | E28: 2615.02 | F28: 2665 | R28: Limite ingresos | S28: ='R.no laboral y R gravables'!G3*30% -> 96600000 | AA28: =AB27+1 -> 18971 | AB28: 31000 | AC28: =AA28*Sheet1!$F$2 -> 944736829 | AD28: =AB28*Sheet1!$F$2 -> 1543769000 | AE28: 0.37 | AF28: (Base gravable en UVT Menos 18970 UVT) *37% + 5901 UVT | AG28: =#REF! -> #REF! | AH28: =((((AG28/Sheet1!$F$2)-18970)*37%)+5901)*Sheet1!$F$2 -> #REF!
B29: 1978 | C29: 273.72 | D29: 2117.65 | E29: 2051.84 | F29: 2091.05 | R29: Valor reportado | S29: ='R.no laboral y R gravables'!E64+'R.no laboral y R gravables'!E65 -> 0 | AA29: =AB28+1 -> 31001 | AB29: En adelante | AC29: =AA29*Sheet1!$F$2 -> 1543818799 | AD29: 9999999999 | AE29: 0.39 | AF29: (Base gravable en UVT Menos 31000 UVT) *39% - 10352 UVT | AG29: =#REF! -> #REF! | AH29: =((((AG29/Sheet1!$F$2)-31000)*39%)+10352)*Sheet1!$F$2 -> #REF!
B30: 1979 | C30: 228.64 | D30: 1768.55 | E30: 1713.59 | F30: 1746.34 | K30: Limite aportes voluntarios cesantias (Renta capital) | L30: Limite aportes voluntarios cesantias (Renta no laboral) | R30: VALOR A REPORTAR | S30: =MIN(S27:S29) -> 0
B31: 1980 | C31: 180.64 | D31: 1398.18 | E31: 1354.73 | F31: 1380.62 | K31: ='R.capital'!G2/12 -> 9118416.7 | L31: ='R.no laboral y R gravables'!G3*25% -> 80500000 | AE31: Renta cedula | AF31: =IF(AND(Sheet1!AG23>Sheet1!AC23,Sheet1!AG23<Sheet1!AD23),Sheet1!AH23,IF(AND(Sheet1!AG24>Sheet1!AC24,Sheet1!AG24<Sheet1!AD24),Sheet1!AH24,IF(AND(Sheet1!AG25>Sheet1!AC25,Sheet1!AG25<Sheet1!AD25),Sheet1!AH25,IF(AND(Sheet1!AG26>Sheet1!AC26,Sheet1!AG26<Sheet1!AD26),Sheet1!AH26,IF(AND(Sheet1!AG27>Sheet1!AC27,Sheet1!AG27<Sheet1!AD27),Sheet1!AH27,IF(AND(Sheet1!AG28>Sheet1!AC28,Sheet1!AG28<Sheet1!AD28),Sheet1!AH28,IF(AND(Sheet1!AG29>Sheet1!AC29,Sheet1!AG29<Sheet1!AD29),Sheet1!AH29,0))))))) -> #REF!
B32: 1981 | C32: 145.15 | D32: 1121.73 | E32: 1086.87 | F32: 1107.65 | K32: =2500*'R.capital'!G68 -> 124497500 | L32: ='R.no laboral y R gravables'!G87*2500 -> 124497500
B33: 1982 | C33: 115.48 | D33: 893.13 | E33: 865.38 | F33: 881.92 | K33: =MIN(K31,K32) -> 9118416.7 | L33: =MIN(L31,L32) -> 80500000
B34: 1983 | C34: 92.79 | D34: 717.7 | E34: 695.39 | F34: 708.68
B35: 1984 | C35: 79.7 | D35: 616.69 | E35: 597.52 | F35: 608.94
B36: 1985 | C36: 67.49 | D36: 535.17 | E36: 518.54 | F36: 528.45
B37: 1986 | C37: 55.27 | D37: 443.02 | E37: 429.25 | F37: 437.46
B38: 1987 | C38: 45.67 | D38: 375.68 | E38: 364.01 | F38: 370.97
B39: 1988 | C39: 37.23 | D39: 283.53 | E39: 274.72 | F39: 279.97
B40: 1989 | C40: 29.17 | D40: 176.77 | E40: 171.27 | F40: 174.55
B41: 1990 | C41: 23.14 | D41: 122.25 | E41: 118.45 | F41: 120.71
B42: 1991 | C42: 17.54 | D42: 85.19 | E42: 82.54 | F42: 84.12 | I42: Limite deducciones
B43: 1992 | C43: 13.82 | D43: 63.81 | E43: 61.83 | F43: 63.01 | I43: Renta laboral | J43: ='R.trabajo y honorarios'!J63 -> 18000000
B44: 1993 | C44: 11.09 | D44: 45.35 | E44: 43.94 | F44: 44.78 | I44: Saldo | J44: =IF(AND(((1200*'R.trabajo y honorarios'!H74)-'R.trabajo y honorarios'!G63)>0,'R.trabajo y honorarios'!J63>0),(1200*'R.trabajo y honorarios'!H74)-'R.trabajo y honorarios'!G63,0) -> 59758800
B45: 1994 | C45: 9.05 | D45: 32.98 | E45: 31.96 | F45: 32.57 | I45: Casilla 50 | J45: =+'R.trabajo y honorarios'!J63 -> 18000000
B46: 1995 | C46: 7.41 | D46: 23.5 | E46: 22.77 | F46: 23.2 | I46: Menor | J46: =+MIN(J43:J45) -> 18000000
B47: 1996 | C47: 6.28 | D47: 17.37 | E47: 16.83 | F47: 17.15
B48: 1997 | C48: 5.41 | D48: 14.41 | E48: 13.97 | F48: 14.23 | I48: DEDUCCION DEPENDIENTES
B49: 1998 | C49: 4.61 | D49: 11.07 | E49: 10.73 | F49: 10.93 | I49: Renta de trabajo | J49: =+'R.trabajo y honorarios'!H4*10% -> 26033300
B50: 1999 | C50: 3.97 | D50: 9.23 | E50: 8.94 | F50: 9.11 | I50: Renta de honorarios | J50: =+'R.trabajo y honorarios'!L4*10% -> 19000000
B51: 2000 | C51: 3.64 | D51: 9.16 | E51: 8.88 | F51: 9.05 | I51: 10% del ingreso | J51: =+('R.trabajo y honorarios'!H4+'R.trabajo y honorarios'!L4)*10% -> 45033300
B52: 2001 | C52: 3.36 | D52: 8.86 | E52: 8.59 | F52: 8.75 | I52: Limite 12 UVT al mes | J52: ='R.trabajo y honorarios'!H74*12*32 -> 19122816 | AR52: 1955 y anteriores | AS52: 3330.67 | AT52: 29515.74
B53: 2002 | C53: 3.13 | D53: 8.19 | E53: 7.94 | F53: 8.09 | I53: Total deduciones | J53: =+MIN(J51:J52) -> 19122816 | AR53: 1956 | AS53: 3264 | AT53: 28925.8
B54: 2003 | C54: 2.93 | D54: 7.35 | E54: 7.12 | F54: 7.26 | I54: Deducción trabajo | J54: =IF('R.trabajo y honorarios'!F64="Si",MIN(J49,J52),0) -> 19122816 | AR54: 1957 | AS54: 3022.24 | AT54: 26783.47
B55: 2004 | C55: 2.75 | D55: 6.92 | E55: 6.7 | F55: 6.83 | I55: Subtotal | J55: =+J53-J54 -> 0 | AR55: 1958 | AS55: 2549.93 | AT55: 22597.37
B56: 2005 | C56: 2.61 | D56: 6.5 | E56: 6.29 | F56: 6.41 | I56: Deducción honorario | J56: =+MIN(J50,J52,J55) -> 0 | AR56: 1959 | AS56: 2331.22 | AT56: 20659.42
B57: 2006 | C57: 2.48 | D57: 6.15 | E57: 5.96 | F57: 6.07 | AR57: 1960 | AS57: 2175.86 | AT57: 19282.42
B58: 2007 | C58: 2.37 | D58: 4.67 | E58: 4.53 | F58: 4.62 | I58: Medicina prepagada | AR58: 1961 | AS58: 2039.82 | AT58: 17979.33
B59: 2008 | C59: 2.24 | D59: 4.16 | E59: 4.03 | F59: 4.11 | I59: Renta laboral | J59: ='R.trabajo y honorarios'!G65 -> 9561408 | AR59: 1962 | AS59: 1919.98 | AT59: 17013.98
B60: 2009 | C60: 2.07 | D60: 3.43 | E60: 3.32 | F60: 3.38 | I60: Saldo | J60: =IF(AND(((192*'R.trabajo y honorarios'!H74)-'R.trabajo y honorarios'!G65)>0,'R.trabajo y honorarios'!J65>0),(192*'R.trabajo y honorarios'!H74)-'R.trabajo y honorarios'!G65,0) -> 0 | AR60: 1963 | AS60: 1793.28 | AT60: 15892.09
B61: 2010 | C61: 2.03 | D61: 3.12 | E61: 3.02 | F61: 3.08 | I61: Casilla | J61: ='R.trabajo y honorarios'!J65 -> 0 | AR61: 1964 | AS61: 1371.23 | AT61: 12152.43
B62: 2011 | C62: 1.97 | D62: 2.86 | E62: 2.77 | F62: 2.82 | I62: Menor | J62: =+MIN(J59:J61) -> 0 | AR62: 1965 | AS62: 1255.34 | AT62: 11124.75
B63: 2012 | C63: 1.9 | D63: 2.39 | E63: 2.32 | F63: 2.36 | AR63: 1966 | AS63: 1095.2 | AT63: 9705.71
B64: 2013 | C64: 1.85 | D64: 2.05 | E64: 1.99 | F64: 2.03 | AR64: 1967 | AS64: 965.6 | AT64: 8557.72
B65: 2014 | C65: 1.82 | D65: 1.81 | E65: 1.76 | F65: 1.79 | I65: APORTES VOLUNTARIOS | AR65: 1968 | AS65: 896.64 | AT65: 7946.04
B66: 2015 | C66: 1.75 | D66: 1.68 | E66: 1.63 | F66: 1.66 | I66: Renta de trabajo | J66: ='R.trabajo y honorarios'!H4/12 -> 21694417 | AR66: 1969 | AS66: 841.18 | AT66: 7454.67
B67: 2016 | C67: 1.64 | D67: 1.6 | E67: 1.55 | F67: 1.58 | I67: Renta de honorarios | J67: ='R.trabajo y honorarios'!L4/12 -> 15833333 | AR67: 1970 | AS67: 773.47 | AT67: 6854.59
B68: 2017 | C68: 1.56 | D68: 1.52 | E68: 1.48 | F68: 1.5 | I68: LIMITE INGRESOS | J68: =+J66+J67 -> 37527750 | AR68: 1971 | AS68: 722, 17 | AT68: 6399.45
B69: 2018 | C69: 1.5 | D69: 1.41 | E69: 1.36 | F69: 1.39 | I69: Limite 2500 UVT | J69: ='R.trabajo y honorarios'!H74*2500 -> 124497500 | AR69: 1972 | AS69: 639.92 | AT69: 5671.81
B70: 2019 | C70: 1.45 | D70: 1.3 | E70: 1.26 | F70: 1.28 | I70: Total deduciones | J70: =+MIN(J68:J69) -> 37527750 | AR70: 1973 | AS70: 562.66 | AT70: 4987.66
B71: 2020 | C71: 1.4 | D71: 1.22 | E71: 1.18 | F71: 1.21 | I71: ='R.trabajo y honorarios'!C67 -> Aportes voluntarios a fondos de cesantias (Inc. 6 Art 126-1 E.T.) | J71: ='R.trabajo y honorarios'!F67 -> 0 | AR71: 1974 | AS71: 459.64 | AT71: 4074.48
B72: 2021 | C72: 1.38 | D72: 1.16 | E72: 1.12 | F72: 1.14 | I72: Deducción trabajo | J72: =MIN(J66,J69,J71) -> 0 | AR72: 1975 | AS72: 367.63 | AT72: 3256.98
B73: 2022 | C73: 1.3 | D73: 1.12 | E73: 1.09 | F73: 1.11 | I73: Subtotal | J73: =+J70-J72 -> 37527750 | AR73: 1976 | AS73: 312.59 | AT73: 2769.95
B74: 2023 | C74: 1.15 | D74: 1.09 | E74: 1.06 | F74: 1.08 | I74: =I71 -> Aportes voluntarios a fondos de cesantias (Inc. 6 Art 126-1 E.T.) | J74: ='R.trabajo y honorarios'!J67 -> 0 | AR74: 1977 | AS74: 249.24 | AT74: 2207.56
B75: 2024 | C75: 1.05 | D75: 1.05 | E75: 1.03 | F75: 1.05 | I75: Deducción honorario | J75: =+MIN(J67,J69,J73,J74) -> 0 | AR75: 1978 | AS75: 195.45 | AT75: 1732.13
AQ76: 1979 | AR76: 163.25 | AS76: 1446.58
B77: Fecha ganancia ocasional | C77: 43465 | AQ77: 1980 | AR77: 128.98 | AS77: 1143.64
AQ78: 1981 | AR78: 103.64 | AS78: 917.52
B79: Rentas exentas henrencia | C79: Rentas exentas Porción conyugal | E79: Rentas exentas Legado | AQ79: 1982 | AR79: 82.46 | AS79: 730.54
B80: =#REF!-#REF!-#REF! -> #REF! | C80: =#REF!-#REF!-#REF! -> #REF! | E80: =#REF!-#REF!-#REF! -> #REF! | AQ80: 1983 | AR80: 66.26 | AS80: 587.04
B81: =#REF! -> #REF! | AQ81: 1984 | AR81: 56.91 | AS81: 504.42
B82: =MIN(B80,B81) -> #REF! | AQ82: 1985 | AR82: 48.19 | AS82: 437.74
AQ83: 1986 | AR83: 39.46 | AS83: 362.37
AQ84: 1987 | AR84: 32.61 | AS84: 307.29
B85: =15000*#REF! -> #REF! | C85: Limite renta exenta casa habitación (Validar si es un limite?¿) | AQ85: 1988 | AR85: 26.59 | AS85: 231.92
AQ86: 1989 | AR86: 20.83 | AS86: 144.59
AQ87: 1990 | AR87: 16.52 | AS87: 99.99
AQ88: 1991 | AR88: 12.53 | AS88: 69.68
AQ89: 1992 | AR89: 9.87 | AS89: 52.19
AQ90: 1993 | AR90: 7.92 | AS90: 37, 10
AQ91: 1994 | AR91: 6.46 | AS91: 26.98
AQ92: 1995 | AR92: 5.29 | AS92: 19.22
AQ93: 1996 | AR93: 4.48 | AS93: 14.21
AQ94: 1997 | AR94: 3.87 | AS94: 11.79
AQ95: 1998 | AR95: 3.29 | AS95: 9.06
AQ96: 1999 | AR96: 2.84 | AS96: 7.55
AQ97: 2000 | AR97: 2.6 | AS97: 7.5
AQ98: 2001 | AR98: 2.4 | AS98: 7.25
AQ99: 2002 | AR99: 2.23 | AS99: 6.7
AQ100: 2003 | AR100: 2.09 | AS100: 6.01
AQ101: 2004 | AR101: 1.97 | AS101: 5.66
AQ102: 2005 | AR102: 1.86 | AS102: 5.31
...

Sheet Deudas
A1: DEUDAS
A2: Renglón 30 | B2: Credito hipotecario banco davivienda No. xxxx | C2: 265000000 | D2: =ROUND(SUM(C2:C41),-3) -> 410000000
B3: Credito libre inversion Banco Davibank | C3: 145000000

Sheet R.trabajo y honorarios
B1: RENTAS DE TRABAJO Y/O HONORARIOS
C2: Concepto | G2: Rentas de trabajo | I2: Renglón 43 | J2: Rentas por honorarios y comp. Serv. Personales sujetos a costos y gastos y no renta exenta num. 10 Art. 206 E.T.
C3: Indique el valor del salario mensual promedio de los últimos 6 meses (numeral 4 Art. 206 E.T.) | H3: =G4/12 -> 13333333
C4: Salarios | G4: 160000000 | H4: =ROUND(SUM(G4:G19),-3) -> 260333000 | L4: =ROUND(SUM(J9:K19),-3) -> 190000000
C5: Bonificaciones, indemnizaciones, y otros ingresos salariales | G5: 10000000
C6: Cesantías consignadas | G6: =G4/12 -> 13333333
C7: Intereses sobre cesantías | G7: 7000000
C8: Cesantías 2016 y anteriores
C9: Honorarios | G9: 70000000 | J9: 190000000 | M9: =+G9*0.25 -> 17500000
C10: Comisiones
C11: Servicios personales
C12: Otros laborales y prestaciones sociales | G12: 0
B20: INCRNGO
C21: Aporte obligatorio a pensión | G21: =G4*5% -> 8000000 | H21: =ROUND(SUM(G21:G32),-3) -> 14400000 | I21: Renglón 44 | L21: =J22+K24+J25+J26+J27+J28+J29+J30+J31+J32 -> 22300000
C22: Bonos de alimentacion
C23: Aporte obligatorio a salud | G23: =G4*4% -> 6400000
C24: Aporte voluntario a fondo obligatorio porvenir - RAIS | G24: =Sheet1!U15 -> 0 | K24: =Sheet1!V17 -> 0
C25: Aporte obligatorio a pension como independiente | J25: 12000000
C26: Aporte obligatorio a salud como independiente | J26: 10300000
C27: Aporte A.R.L. NO TIENE EFECTO FISCAL
C28: Salarios funcionarios de organismos multilaterales
C29: Salarios y/o honorarios vinculados proyectos de investigación (Art. 57-2 E.T.)
C30: Apoyos ecónomicos (Art 46 E.T.)
B33: Costos y deducciones
H34: 0 | I34: Renglón 45 | L34: =ROUND(MIN(SUM(J34:K47),K9),-3) -> 83000000
C36: Costos honorarios | J36: 83000000
C48: Total rentas exentas y deducciones | H48: =SUM(H34:H47) -> 0 | L48: =SUM(L34) -> 83000000
B49: Rentas exentas y deducciones
C50: Aporte voluntario a pension | F50: 12000000 | G50: =Sheet1!S9 -> 22000000 | H50: =ROUND(SUM(G50:G67),-3) -> 112609000 | I50: R. 47 | J50: 0 | K50: =Sheet1!S18 -> 0 | L50: =ROUND(SUM(K52:K67),-3) -> 18000000
C51: Ahorro en cuenta AFC y/o AVC | F51: 10000000
C52: Cesantías consignadas | F52: =G6 -> 13333333 | G52: =IF(AND(Sheet1!K14>Sheet1!I7,(Sheet1!K14<Sheet1!K7)),Sheet1!K15*Sheet1!P7,IF(AND(Sheet1!K14>Sheet1!I8,(Sheet1!K14<Sheet1!K8)),Sheet1!K15*Sheet1!P8,IF(AND(Sheet1!K14>Sheet1!I9,(Sheet1!K14<Sheet1!K9)),Sheet1!K15*Sheet1!P9,IF(AND(Sheet1!K14>Sheet1!I9,(Sheet1!K14<Sheet1!K9)),Sheet1!K15*Sheet1!P9,IF(AND(Sheet1!K14>Sheet1!I10,(Sheet1!K14<Sheet1!K10)),Sheet1!K15*Sheet1!P10,IF(AND(Sheet1!K14>Sheet1!I11,(Sheet1!K14<Sheet1!K11)),Sheet1!K15*Sheet1!P11,IF(AND(Sheet1!K14>Sheet1!I12,(Sheet1!K14<Sheet1!K12)),Sheet1!K15*Sheet1!P12,Sheet1!K15))))))) -> 20333333 | I52: Renglón 48
C53: Intereses sobre cesantías | F53: =G7 -> 7000000
C54: Retiro de cesantias antes del año 2016 (Ley 1819 del 2016) No limitada | F54: =G8 -> 0
C55: Indemizaciones por accidente de trabajo (Numeral 1. Art. 206 E.T.)
C56: Indemizaciones por protección a maternidad (Numeral 2. Art. 206 E.T.)
C57: Gastos de entierro (Numeral 3. Art. 206 E.T.)
C58: Seguro por muerte, compensaciones por muerte y prestaciones sociales de FFMM. (Numeral 6 Art. 206 E.T.). No limitada
C59: Exceso de salario fuerzas militares. (Numeral 8 Art. 206 E.T.). No limitada
C60: Gastos de representación rectores y profesores universidades publicas. (Numeral 9 Art. 206 E.T.). No limitada
C61: Prima especial y prima de costo de vida servidores publicos - Diplomaticos. ( Art. 206-1 E.T.). No limitada
C62: Renta exenta del 25% | G62: =MIN((H4-H21-'R.trabajo y honorarios'!G52-G55-G56-G57-G58-G59-G60-G61-'R.trabajo y honorarios'!G50-G64-G65-G63)*25%,790*H74) -> 39341210
C63: Intereses por prestamos de vivienda (casa habitación) | F63: 0 | G63: =IF(F63>(1200*H74),(1200*H74),F63) -> 0 | I63: R. 50 | J63: 18000000 | K63: =Sheet1!J46 -> 18000000
C64: Deduccion por dependientes | F64: Si | G64: =IF(F64="Si",MIN(Sheet1!J49,Sheet1!J52),0) -> 19122816 | I64: Renglón 51 | J64: No | K64: =IF(J64="Si",MIN(Sheet1!J56,Sheet1!J52),0) -> 0
C65: Deducción por medicina prepagada y plan complementario | F65: 11000000 | G65: =IF(F65>(H74*192),(H74*192),F65) -> 9561408 | J65: 0 | K65: =Sheet1!J62 -> 0
C66: G.M.F. | F66: 4500000 | G66: =F66/2 -> 2250000 | K66: =J66/2 -> 0
C67: Aportes voluntarios a fondos de cesantias (Inc. 6 Art 126-1 E.T.) | F67: 0 | G67: =Sheet1!J72 -> 0 | K67: =Sheet1!J75 -> 0
C68: Total rentas exentas y deducciones | H68: =SUM(H50:H67) -> 112609000 | L68: =SUM(L50) -> 18000000
C70: Compensaciones por pérdidas
C71: Compensación de perdidas | L71: =K71 -> 0
B74: Valor UVT | H74: 49799

Sheet Dependientes 
B3: Número de dependientes | C3: 2 | D3: Sólo digite el número de dependientes
B4: Deducción adicional individual por dependiente | C4: =72*47065 -> 3388680
B6: Nombre del dependiente económico | C6: Deducción
B7: Juan | C7: {=_xlfn.IFS(C3=1,C4,C3=2,C4,C3=3,C4,C3=4,C4,C3=0,0)} -> 3388680
B8: Pedro | C8: {=0+_xlfn.IFS(C3=2,C4,C3=3,C4,C3=4,C4,C3=1,0,C3=0,0)} -> 3388680
B9: Sandra | C9: {=0+_xlfn.IFS(C3=1,0,C3=2,0,C3=3,C4,C3=4,C4,C3=0,0)} -> 0
B10: Camilo | C10: {=0+_xlfn.IFS(C3=1,0,C3=2,0,C3=3,0,C3=4,C4,C3=0,0)} -> 0
B11: Total Duducción Adicional | C11: =ROUND(SUM(C7:C10),-3) -> 6777000
D12: =72*47065 -> 3388680
B14: La deducción por dependientes a que se refieren el inciso 2 del numeral 3 del artículo 336 y la del artículo 387 del Estatuto Tributario aplican únicamente a los ingresos provenientes de rentas de trabajo y un mismo dependiente solo dará lugar a una de estas dos deducciones, excepto cuando se tenga rentas provenientes de una relación laboral y legal o reglamentaria: caso en el cual se podrá aplicar ambas deducciones por un mismo dependiente."

Sheet Fac. Elctrónicas
B2: No factura | C2: Valor factura incluido IVA | D2: Derecho deducción. | E2: 5. Las personas naturales que declaren ingresos de la cédula general a los que se refiere el artículo 335 de este Estatuto, que adquieran bienes y/o servicios, podrán solicitar como deducción en el impuesto sobre la renta, independientemente que tenga o no relación de causalidad con la actividad productora de renta del contribuyente, el uno por ciento (1%) del valor de las adquisiciones, sin que exceda doscientas cuarenta (240) UVT en el respectivo año gravable, siempre que se cumpla con los siguientes requisitos: 5.1. Que la adquisición del bien y/o del servicio no haya sido solicitada como costo o deducción en el impuesto sobre la renta, impuesto descontable en el impuesto sobre las ventas -IVA, ingreso no constitutivo de renta ni ganancia ocasional, renta exenta, descuento tributario u otro tipo de beneficio o crédito fiscal. 5.2. Que la adquisición del bien y/o del servicio esté soportada con factura electrónica de venta con validación previa, en donde se identifique el adquirente con nombres y apellidos y el número de identificación tributaria -NIT o número de documento de identificación, y con el cumplimiento de todos los demás requisitos exigibles para este sistema de facturación. 5.3. Que la factura electrónica de venta se encuentre pagada a través de tarjeta débito/crédito o cualquier medio electrónico en el cual intervenga una entidad vigilada por la Superintendencia Financiera o quien haga sus veces dentro del periodo gravable en el cual se solicita la deducción de que trata el presente numeral. 5.4. Que la factura electrónica de venta haya sido expedida por sujetos obligados a expedirla.
D3: =C3*1% -> 0
C4: 180000000 | D4: =C4*1% -> 1800000
D5: =C5*1% -> 0
D6: =C6*1% -> 0
D7: =C7*1% -> 0
D8: =C8*1% -> 0
D9: =C9*1% -> 0
D10: =C10*1% -> 0
D11: =C11*1% -> 0
D12: =C12*1% -> 0
D13: =C13*1% -> 0
D14: =C14*1% -> 0
D15: =C15*1% -> 0
D16: =C16*1% -> 0
... D26: =C26*1% -> 0
B27: TOTAL 1% COMPRAS REALIZADAS | D27: =SUM(D3:D26) -> 1800000
B28: LÍMITE (Art 336 Numeral 5 - 240 UVT) | D28: =(240*49065) -> 11775600
B29: Deducción a tomar | D29: =MIN(D27:D28) -> 1800000

Sheet R.capital
B1: RENTAS DE CAPITAL
B2: Rengón 58 | C2: Rendimientos financieros con componente inflacionario | G2: =ROUND((F3+F13+F21+F29),-3) -> 109421000
F3: =SUM(E3:E11) -> 17340000
C4: Rendimientos financieros banco davienda | E4: 12340000
C5: Rendimientos financieros banco caja social | E5: 5000000
C12: Intereses de fuente nacional y del exterior
F13: =SUM(E13:E19) -> 2081250
C19: Ingresos presuntos | E19: ='tabl int presunt'!G18 -> 2081250
C20: Arrendamientos
F21: =SUM(E21:E27) -> 90000000
C23: Arriendo oficina calle 93 | E23: 90000000
E25: 0
C28: Regalias y propiedad intelectual
F29: =SUM(E29:E35) -> 0
B36: Renglón 59 | C36: I.N.C.R.N.G.O.
C37: Aporte obligatorio a pensión | F37: 3000000 | G37: =ROUND(SUM(F37:F43),-3) -> 15112000
C38: Aporte obligatorio a salud | F38: 2500000
C39: Aporte obligatorio a A.R.L. | F39: 0
C40: Aporte voluntario a fondo obligatorio - RAIS | E40: 0 | F40: =Sheet1!W15 -> 0
C41: Componente inflacionario | F41: =F3*55.43% -> 9611562
B44: Renglón 60 | C44: Costos y gastos procedentes
G45: =ROUND(SUM(F45:F51),-3) -> 20000000
C46: Predial de la oficina calle 93 | F46: 13000000
C47: Remodelacion | F47: 7000000
C48: Cuotas de administracion ?????
C52: Rentas exentas y deducciones
B53: R.63 | C53: Aporte voluntario a pensión | F53: =Sheet1!S24 -> 0 | G53: =SUM(F55:F57) -> 0
C54: Ahorro en cuenta AFC y/o AVC | E54: 0
B55: R. 66 | C55: Intereses por prestamos de vivienda | E55: 0 | F55: =IF(E55>(1200*G68),(1200*G68),E55) -> 0
B56: R.67 | C56: G.M.F. | E56: 0 | F56: =E56*50% -> 0
C57: Aportes voluntarios a fondos de cesantias | E57: 0 | F57: =IF(E57>Sheet1!K33,Sheet1!K33,E57) -> 0
B58: Renglón 62 | C58: Rentas líquidas pasivas de capital
G59: =ROUND(SUM(F59:F63),-3) -> 0
B65: R. 72 | C65: Compensaciones por pérdidas
C66: Compensación de perdidas | G66: =F66 -> 0
C68: Valor UVT | G68: ='R.trabajo y honorarios'!H74 -> 49799

Sheet tabl int presunt
B1: CÁLCULO DEL INTERES PRESUNTO
B2: DECRETO 771 12 JULIO DE 2025
B3: Rend. Mínimo | G3: 0.0925
B4: Mensual | G4: =G3/12 -> 0.0077083333
B5: Mes | C5: Saldo Inicial | D5: Nuevo Préstamo | E5: Abonos | F5: Saldo Final | G5: Int. Presunto
B6: Enero | C6: 0 | F6: =C6+D6-E6 -> 0 | G6: =C6*$G$4 -> 0
B7: Febrero | C7: =F6 -> 0 | F7: =C7+D7-E7 -> 0 | G7: =C7*$G$4 -> 0
B8: Marzo | C8: =F7 -> 0 | F8: =C8+D8-E8 -> 0 | G8: =C8*$G$4 -> 0
B9: Abril | C9: =F8 -> 0 | D9: 0 | F9: =C9+D9-E9 -> 0 | G9: =C9*$G$4 -> 0
B10: Mayo | C10: =F9 -> 0 | D10: 0 | F10: =C10+D10-E10 -> 0 | G10: =C10*$G$4 -> 0
B11: Junio | C11: =F10 -> 0 | F11: =C11+D11-E11 -> 0 | G11: =C11*$G$4 -> 0
B12: Julio | C12: =F11 -> 0 | D12: 50000000 | F12: =C12+D12-E12 -> 50000000 | G12: =C12*$G$4 -> 0
B13: Agosto | C13: =F12 -> 50000000 | F13: =C13+D13-E13 -> 50000000 | G13: =C13*$G$4 -> 385416.67
B14: Septiembre | C14: =F13 -> 50000000 | F14: =C14+D14-E14 -> 50000000 | G14: =C14*$G$4 -> 385416.67
B15: Octubre | C15: =F14 -> 50000000 | D15: 10000000 | F15: =C15+D15-E15 -> 60000000 | G15: =C15*$G$4 -> 385416.67
B16: Noviembre | C16: =F15 -> 60000000 | F16: =C16+D16-E16 -> 60000000 | G16: =C16*$G$4 -> 462500
B17: Diciembre | C17: =F16 -> 60000000 | E17: 60000000 | F17: =C17+D17-E17 -> 0 | G17: =C17*$G$4 -> 462500
B18: Total intereses presunto | G18: =SUM(G6:G17) -> 2081250

Sheet R.no laboral y R gravables
B1: Renglón 74 | C1: RENTAS NO LABORALES
C2: Ingresos
C3: Venta de un vehiculo | F3: 67000000 | G3: =ROUND(SUM(F3:F16),-3) -> 322000000
C4: Liquidacion de una sociedad conyugal | F4: 198000000
C5: Otros ingresos | F5: 22000000
C6: Ingreso por seguro de daño art. 44 E.T. daño emergente | F6: 35000000
B17: Renglón 75 | C17: Devoluciones, rebajas y descuentos
G18: =ROUND(SUM(F18:F22),-3) -> 0
B23: Renglón 76 | C23: I.N.C.R.N.G.O.
C24: Aporte voluntario a fondo obligatorio - RAIS | F24: =Sheet1!X15 -> 0 | G24: =ROUND(SUM(F24:F36),-3) -> 233000000
C25: Aporte obligatorio a salud
C26: Aporte Obligatorio a Pensión
C27: Aporte riesgo laboral
C28: Seguro de daño componente daño emergente | F28: =F6 -> 35000000
C29: Ganancial liquid sociedad conyugal art. 47 E.T. | F29: =F4 -> 198000000
B37: Renglón 77 | C37: Costos y gastos procedentes
G38: =SUM(F38:F56) -> 64000000
C39: Costo del vehiculo | F39: =64000000 -> 64000000
B57: Renglón 79 | C57: Rentas líquidas pasivas no laborales E.C.E
G58: 0
B63: Rentas exentas y deducciones
B64: R. 80 | C64: Aporte voluntario a pensión | E64: 0 | F64: =Sheet1!S30 -> 0 | G64: =SUM(F66:F71) -> 0
C65: Ahorro en cuenta AFC y/o AVC | E65: 0
B66: R. 81 | C66: Rentas por servicios hoteleros en nuevos o remodelados (No limitada)
C67: Otras rentas exentas
B69: R. 83 | C69: Intereses por prestamos de vivienda | F69: =IF(E69>(1200*G87),(1200*G87),E69) -> 0
B70: R. 84 | C70: G.M.F. | F70: =E70/2 -> 0
C71: Aportes voluntarios a fondos de cesantias | F71: =IF(E71>Sheet1!L33,Sheet1!L33,E71) -> 0
B72: Renglón 79 | C72: Rentas líquidas pasivas de capital
G73: =ROUND(SUM(F73:F77),-3) -> 0
B79: R. 89 | C79: Compensaciones por pérdidas
C80: Compensación de perdidas | G80: =F80 -> 0
B82: Renglón 96 | C82: Rentas liquidas gravables Art 239-1 y otras
C83: Activos omitidos | G83: =SUM(F83:F85) -> 0
C84: Pasivos inexistentes | F84: 0
C85: Diferencia por comparación patrimonial no justificada | F85: 0
B87: Valor UVT | G87: ='R.capital'!G68 -> 49799

Sheet G.OCAS
A1: GANANCIA OCASIONAL
A2: Renglón 111 | B2: Venta de inmuebles diferente a vivienda | C2: Tipo de inmueble/ Acciones | D2: Precio de venta | E2: Costo fiscal por ganancia ocasional
C3: Casa calle 3 cra 4 | D3: 450000000 | E3: Costo Fiscal año anterior (Avaluo catastral o autoavaluo art. 72 E.T.) | F3: 0 | G3: =IF(ROUND(SUM(F3+F7+F8+F9),-3)>D3,D3,ROUND(SUM(F3+F7+F8+F9),-3)) -> 450000000 | H3: Diligencie esta sección solo si en año anterior el VALOR PATRIMONIAL fue determinado con el valor del predial o si desea determinar el costo de la ganancia ocasional con el valor de compra más reajustes fiscales
E4: Costo de adquisición | F4: 305000000
E5: Fecha de compra | F5: 41959
E6: Fecha de venta | F6: 45838
E7: Costo fiscal reajustado | F7: =+'REAJUST FISCAL'!F57 -> 5.8102271e+08
E8: (+) mejoras en el año de la venta | F8: 0
E9: (+) Valorización en el año de la venta | F9: 0
E10: Costo de adquisición | F10: 0 | G10: =IF(ROUND(SUM(F14+F15+F16),-3)>D3,D3,ROUND(SUM(F14+F15+F16),-3)) -> 0 | H10: Diligencie esta sección solo si en año anterior el valor patrimonial lo determino de acuerdo al art. 73 E.T.
E11: Bines raices o acciones o aportes | F11: Bienes urbanos
E12: Año de adquisición | F12: 2001
E13: Ajuste incremento porcentual del v/r. de la propiedad raíz entre el año de la compra y el año de la venta | F13: =IF(G.OCAS!F11="Acciones y aportes",VLOOKUP(G.OCAS!F12,Sheet1!$B$5:$F$75,2),IF(G.OCAS!F11="BIENES URBANOS",VLOOKUP(G.OCAS!F12,Sheet1!$B$5:$F$75,3),IF(G.OCAS!F11="BIENES RURALES",VLOOKUP(G.OCAS!F12,Sheet1!$B$5:$F$75,5),IF(G.OCAS!F11="Bienes Raíces Rurales dedicados a actividades agropecuarias",VLOOKUP(G.OCAS!F12,Sheet1!$B$5:$F$75,4),0)))) -> 8.86
E14: Costo reajustado | F14: =+F10*G.OCAS!F13 -> 0
E15: (+) mejoras
E16: (+) Valorización
E17: Costo Fiscal año anterior (Avaluo catastral o autoavaluo art. 72 E.T.) | F17: 0 | G17: =IF(ROUND(SUM(F17+F21+F22+F23),-3)>D17,D17,ROUND(SUM(F17+F21+F22+F23),-3)) -> 0 | H17: Diligencie esta sección solo si en año anterior el VALOR PATRIMONIAL fue determinado con el valor del predial o si desea determinar el costo de la ganancia ocasional con el valor de compra más reajustes fiscales
E18: Costo de adquisición | F18: 150000000
E19: Fecha de compra | F19: 44392
E20: Fecha de venta | F20: 45856
E21: Costo fiscal reajustado | F21: =+'REAJUST FISCAL'!F117 -> 2.1563405e+08
E22: (+) mejoras en el año de la venta
E23: (+) Valorización en el año de la venta
E24: Costo de adquisición | F24: 0 | G24: =IF(ROUND(SUM(F28+F29+F30),-3)>D17,D17,ROUND(SUM(F28+F29+F30),-3)) -> 0 | H24: Diligencie esta sección solo si en año anterior el valor patrimonial lo determino de acuerdo al art. 73 E.T.
E25: Bines raices o acciones o aportes | F25: Bienes urbanos
E26: Año de adquisición | F26: 2021
E27: Ajuste incremento porcentual del v/r. de la propiedad raíz entre el año de la compra y el año de la venta | F27: =IF(G.OCAS!F25="Acciones y aportes",VLOOKUP(G.OCAS!F26,Sheet1!$B$5:$F$75,2),IF(G.OCAS!F25="BIENES URBANOS",VLOOKUP(G.OCAS!F26,Sheet1!$B$5:$F$75,3),IF(G.OCAS!F25="BIENES RURALES",VLOOKUP(G.OCAS!F26,Sheet1!$B$5:$F$75,5),IF(G.OCAS!F25="Bienes Raíces Rurales dedicados a actividades agropecuarias",VLOOKUP(G.OCAS!F26,Sheet1!$B$5:$F$75,4),0)))) -> 1.16
E28: Costo reajustado | F28: =+F24*F27 -> 0
E29: (+) mejoras
E30: (+) Valorización
B31: Venta casa habitación | C31: 0 | D31: 0 | E31: Costo Fiscal año anterior (Avaluo catastral o autoavaluo art. 72 E.T.) | F31: 0 | G31: =IF(ROUND(SUM(F31+F35+F36+F37),-3)>D31,D31,ROUND(SUM(F31+F35+F36+F37),-3)) -> 0 | H31: Diligencie esta sección solo si en año anterior el VALOR PATRIMONIAL fue determinado con el valor del predial o si desea determinar el costo de la ganancia ocasional con el valor de compra más reajustes fiscales
E32: Costo de adquisición | F32: 0
E33: Fecha de compra | F33: 44576
E34: Fecha de venta | F34: 45321
E35: Costo fiscal reajustado
E36: (+) mejoras en el año de la venta
E37: (+) Valorización en el año de la venta
E38: Costo de adquisición | F38: 0 | G38: =IF(ROUND(SUM(F42+F43+F44),-3)>D31,D31,ROUND(SUM(F42+F43+F44),-3)) -> 0 | H38: Diligencie esta sección solo si en año anterior el valor patrimonial lo determino de acuerdo al art. 73 E.T.
E39: Bines raices o acciones o aportes | F39: Bienes urbanos
E40: Año de adquisición | F40: 2021
E41: Ajuste incremento porcentual del v/r. de la propiedad raíz entre el año de la compra y el año de la venta | F41: =IF(G.OCAS!F39="Acciones y aportes",VLOOKUP(G.OCAS!F40,Sheet1!$B$5:$F$75,2),IF(G.OCAS!F39="BIENES URBANOS",VLOOKUP(G.OCAS!F40,Sheet1!$B$5:$F$75,3),IF(G.OCAS!F39="BIENES RURALES",VLOOKUP(G.OCAS!F40,Sheet1!$B$5:$F$75,5),IF(G.OCAS!F39="Bienes Raíces Rurales dedicados a actividades agropecuarias",VLOOKUP(G.OCAS!F40,Sheet1!$B$5:$F$75,4),0)))) -> 1.16
E42: Costo reajustado | F42: =+F38*F41 -> 0
E43: (+) mejoras
E44: (+) Valorización
C45: Valor castastral o autovaluo año venta (2022)
B46: Herencias | C46: Inmueble de vivienda del causante | D46: 0
C47: Demás inmuebles diferentes al de la vivienda del causante | D47: 0
C48: Acciones | D48: 0
C49: Joyas | D49: 0
C50: Vehículo | D50: 0
C51: Etc. | D51: 0
C52: Etc. | D52: 0
C53: Etc. | D53: 0
B54: Porción conyugal | D54: 0
D55: 0
D56: 0
B57: Legado | D57: 0
D58: 0
D59: 0
B60: Donaciones y otros Actos | D60: 0
C61: Nuda propiedad | D61: 0
D62: 0
B63: Loterias, rifas, chances | D63: 0
D64: 0
D65: 0
D66: 0
B67: Ingreso por ganancia ocasional al 15% | D67: =ROUND(SUM(D3:D62),-3) -> 450000000 | E67: Total costo por ganancia ocasional | G67: =ROUND(SUM(G3:G44),-3) -> 450000000
B68: Ingreso por ganancia ocasional al 20% | D68: =ROUND(SUM(D63:D66),-3) -> 0
B69: Total ingreso por ganancia ocasional | D69: =SUM(D67:D68) -> 450000000
A72: GANANCIAS OCASIONALES EXENTAS
A73: Renglón 115 | C73: Concepto | E73: Porción conyugal | F73: Legado | G73: Donaciones y otros actos jurídico intervivos | H73: Venta casa habitación
C74: Total ingresos por G.O. | D74: =ROUND(SUM(D46:D53),-3) -> 0 | E74: =ROUND(SUM(D54:D56),-3) -> 0 | F74: =ROUND(SUM(D57:D59),-3) -> 0 | G74: =ROUND(SUM(D60:D62),-3) -> 0 | H74: =ROUND(SUM(D31),-3) -> 0
C75: Total costo por G.O. | D75: N/A | E75: N/A | F75: N/A | G75: N/A | H75: =ROUND(SUM(G31:G44),-3) -> 0
C76: Ganancia ocasional inicial | D76: =+D74 -> 0 | E76: =+E74 -> 0 | F76: =+F74 -> 0 | G76: =+G74 -> 0 | H76: =H74-H75 -> 0
C77: Indique el numero de legitimarios | D77: 1 | E77: N/A | F77: N/A | G77: N/A | H77: N/A
C78: g.o. exenta num. 1 art. 307 E.T. | D78: =IF(MAX(D46)>E84,E84,MAX(D46)) -> 0 | E78: N/A | F78: N/A | G78: N/A | H78: N/A
C79: g.o. exenta num. 2 art. 307 E.T. | D79: =IF(MAX(D47)>E85,E85,MAX(D47)) -> 0 | E79: N/A | F79: N/A | G79: N/A | H79: N/A
C80: g.o. exenta num. 3 art. 307 E.T. | D80: =MIN(D76+E76+F76-D78-D79,E86) -> 0 | G80: N/A | H80: N/A
C81: g.o. exenta num. 4 art. 307 E.T. 20% maximo 1.625 uvt | D81: N/A | E81: N/A | F81: N/A | G81: =MIN(E87,G74*20%) -> 0 | H81: N/A
C82: g.o. exenta art. 311-1 E.T. | D82: N/A | E82: N/A | F82: N/A | G82: N/A | H82: =IF(H76>E88,E88,H76) -> 0
C83: Total ganancias ocasionales exentas | D83: =ROUND((D78+D79+D80+G81+H82),-3) -> 0
C84: g.o. exenta num. 1 art. 307 E.T. | D84: 13000 | E84: =D84*$E$89 -> 611845000 | F84: =E84/D77 -> 611845000
C85: g.o. exenta num. 2 art. 307 E.T. | D85: 6500 | E85: =D85*$E$89 -> 305922500
C86: g.o. exenta num. 3 art. 307 E.T. | D86: 3250 | E86: =D86*$E$89 -> 152961250
C87: g.o. exenta num. 4 art. 307 E.T. | D87: 1625 | E87: =D87*$E$89 -> 76480625
C88: g.o. art. 311-1 E.T. | D88: 5000 | E88: =D88*$E$89 -> 235325000
C89: Valor UVT | E89: 47065
B92: IMPUESTO DE GANANCIA OCASIONAL
B93: Renglón 128 | C93: Concepto | D93: Valor
C94: Ingreso por ganancia ocasional a la tarifa del 15% | D94: =D67 -> 450000000
C95: (-) Costo por ganancia ocasional | D95: =G67 -> 450000000
C96: (-) Ganancia ocasional no gravada y exenta | D96: =ROUND(D83,-3) -> 0
C97: (=) Ganancia Ocasional Gravable a la tarifa del 15% | D97: =D94-D95-D96 -> 0
C98: Ingreso por ganancia ocasional a la tarifa del 20% | D98: =D68 -> 0
C99: Impuesto de Ganancia Ocasionales 15% | D99: =ROUND((D97*0.15),-3) -> 0
C100: Impuesto de Ganancia Ocasionales 20% | D100: =ROUND((D98*0.2),-3) -> 0
C101: Total impuesto por ganancia ocasional | D101: =ROUND(SUM(D99:D100),-3) -> 0

Sheet REAJUST FISCAL
B4: AÑO | C4: % | D4: VALOR BASE | E4: REAJUSTE | F4: TOTAL REAJUSTADO | G4: Normatividad
B5: 1974 | C5: 0.08 | D5: =+IF(B5='REAJUST FISCAL'!$I$11,G.OCAS!$F$4,0) -> 0 | E5: =+IF(B5=$I$11,C5*$M$11*D5,IF(B5=$I$12,C5*$M$12*D5,C5*D5)) -> 0 | F5: =+'REAJUST FISCAL'!D5+E5 -> 0 | G5: Decreto 2247 de 1974
B6: 1975 | C6: 0.08 | D6: =+IF(B6='REAJUST FISCAL'!$I$11,G.OCAS!$F$4,F5) -> 0 | E6: =+IF(B6=$I$11,C6*$M$11*D6,IF(B6=$I$12,C6*$M$12*D6,C6*D6)) -> 0 | F6: =+D6+E6 -> 0 | G6: Decreto 187 de 1975
B7: 1976 | C7: 0.08 | D7: =+IF(B7='REAJUST FISCAL'!$I$11,G.OCAS!$F$4,F6) -> 0 | E7: =+IF(B7=$I$11,C7*$M$11*D7,IF(B7=$I$12,C7*$M$12*D7,C7*D7)) -> 0 | F7: =+D7+E7 -> 0 | G7: Ley 19 de 1976
B8: 1977 | C8: 0.14 | D8: =+IF(B8='REAJUST FISCAL'!$I$11,G.OCAS!$F$4,F7) -> 0 | E8: =+IF(B8=$I$11,C8*$M$11*D8,IF(B8=$I$12,C8*$M$12*D8,C8*D8)) -> 0 | F8: =+D8+E8 -> 0 | G8: Ley 54 de 1977
B9: 1978 | C9: 0.095 | D9: =+IF(B9='REAJUST FISCAL'!$I$11,G.OCAS!$F$4,F8) -> 0 | E9: =+IF(B9=$I$11,C9*$M$11*D9,IF(B9=$I$12,C9*$M$12*D9,C9*D9)) -> 0 | F9: =+D9+E9 -> 0 | G9: Decreto 2114 de 1978
B10: 1979 | C10: 0.244 | D10: =+IF(B10='REAJUST FISCAL'!$I$11,G.OCAS!$F$4,F9) -> 0 | E10: =+IF(B10=$I$11,C10*$M$11*D10,IF(B10=$I$12,C10*$M$12*D10,C10*D10)) -> 0 | F10: =+D10+E10 -> 0 | G10: Ley 20 de 1979 /Decreto 2326 de 1979
B11: 1980 | C11: 0.2472 | D11: =+IF(B11='REAJUST FISCAL'!$I$11,G.OCAS!$F$4,F10) -> 0 | E11: =+IF(B11=$I$11,C11*$M$11*D11,IF(B11=$I$12,C11*$M$12*D11,C11*D11)) -> 0 | F11: =+D11+E11 -> 0 | G11: Decreto 2534 de 1980 | I11: =+YEAR(G.OCAS!F5) -> 2014 | J11: =+CONCATENATE("31/12/",+I11) -> 31/12/2014 | K11: 360 | L11: =+_xlfn.DAYS(J11,G.OCAS!F5) -> 45 | M11: =+L11/K11 -> 0.125 | N11: =+M11*C50 -> 0.0042
B12: 1981 | C12: 0.2775 | D12: =+IF(B12='REAJUST FISCAL'!$I$11,G.OCAS!$F$4,F11) -> 0 | E12: =+IF(B12=$I$11,C12*$M$11*D12,IF(B12=$I$12,C12*$M$12*D12,C12*D12)) -> 0 | F12: =+D12+E12 -> 0 | G12: Decreto 2655 de 1981 | I12: =+YEAR(G.OCAS!F6) -> 2025 | J12: 45292 | K12: 360 | L12: =+_xlfn.DAYS(G.OCAS!F6,J12) -> 546 | M12: =+L12/K12 -> 1.5166667
B13: 1982 | C13: 0.2347 | D13: =+IF(B13='REAJUST FISCAL'!$I$11,G.OCAS!$F$4,F12) -> 0 | E13: =+IF(B13=$I$11,C13*$M$11*D13,IF(B13=$I$12,C13*$M$12*D13,C13*D13)) -> 0 | F13: =+D13+E13 -> 0 | G13: Decreto 2809 de 1982
B14: 1983 | C14: 0.1942 | D14: =+IF(B14='REAJUST FISCAL'!$I$11,G.OCAS!$F$4,F13) -> 0 | E14: =+IF(B14=$I$11,C14*$M$11*D14,IF(B14=$I$12,C14*$M$12*D14,C14*D14)) -> 0 | F14: =+D14+E14 -> 0 | G14: Ley 9 de 1983/Decreto 2124 de 1983
B15: 1984 | C15: 0.1517 | D15: =+IF(B15='REAJUST FISCAL'!$I$11,G.OCAS!$F$4,F14) -> 0 | E15: =+IF(B15=$I$11,C15*$M$11*D15,IF(B15=$I$12,C15*$M$12*D15,C15*D15)) -> 0 | F15: =+D15+E15 -> 0 | G15: Decreto 1843 de 1984
B16: 1985 | C16: 0.2451 | D16: =+IF(B16='REAJUST FISCAL'!$I$11,G.OCAS!$F$4,F15) -> 0 | E16: =+IF(B16=$I$11,C16*$M$11*D16,IF(B16=$I$12,C16*$M$12*D16,C16*D16)) -> 0 | F16: =+D16+E16 -> 0 | G16: Decreto 2032 de 1985
B17: 1986 | C17: 0.163 | D17: =+IF(B17='REAJUST FISCAL'!$I$11,G.OCAS!$F$4,F16) -> 0 | E17: =+IF(B17=$I$11,C17*$M$11*D17,IF(B17=$I$12,C17*$M$12*D17,C17*D17)) -> 0 | F17: =+D17+E17 -> 0 | G17: Ley 75 de 1986/Decreto 2444 de 1986
B18: 1987 | C18: 0.1679 | D18: =+IF(B18='REAJUST FISCAL'!$I$11,G.OCAS!$F$4,F17) -> 0 | E18: =+IF(B18=$I$11,C18*$M$11*D18,IF(B18=$I$12,C18*$M$12*D18,C18*D18)) -> 0 | F18: =+D18+E18 -> 0 | G18: Decreto 59 de 1987
B19: 1988 | C19: 0.2365 | D19: =+IF(B19='REAJUST FISCAL'!$I$11,G.OCAS!$F$4,F18) -> 0 | E19: =+IF(B19=$I$11,C19*$M$11*D19,IF(B19=$I$12,C19*$M$12*D19,C19*D19)) -> 0 | F19: =+D19+E19 -> 0 | G19: Decreto 2540 de 1987
B20: 1989 | C20: 0.2799 | D20: =+IF(B20='REAJUST FISCAL'!$I$11,G.OCAS!$F$4,F19) -> 0 | E20: =+IF(B20=$I$11,C20*$M$11*D20,IF(B20=$I$12,C20*$M$12*D20,C20*D20)) -> 0 | F20: =+D20+E20 -> 0 | G20: Decreto 2671 de 1988
B21: 1990 | C21: 0.2664 | D21: =+IF(B21='REAJUST FISCAL'!$I$11,G.OCAS!$F$4,F20) -> 0 | E21: =+IF(B21=$I$11,C21*$M$11*D21,IF(B21=$I$12,C21*$M$12*D21,C21*D21)) -> 0 | F21: =+D21+E21 -> 0 | G21: Decreto 624 de 1989 / Decreto 3018 de 1989
B22: 1991 | C22: 0.3004 | D22: =+IF(B22='REAJUST FISCAL'!$I$11,G.OCAS!$F$4,F21) -> 0 | E22: =+IF(B22=$I$11,C22*$M$11*D22,IF(B22=$I$12,C22*$M$12*D22,C22*D22)) -> 0 | F22: =+D22+E22 -> 0 | G22: Decreto 3100 de 1990
B23: 1992 | C23: 0.2981 | D23: =+IF(B23='REAJUST FISCAL'!$I$11,G.OCAS!$F$4,F22) -> 0 | E23: =+IF(B23=$I$11,C23*$M$11*D23,IF(B23=$I$12,C23*$M$12*D23,C23*D23)) -> 0 | F23: =+D23+E23 -> 0 | G23: Certificación DANE 102300
B24: 1993 | C24: 0.262 | D24: =+IF(B24='REAJUST FISCAL'!$I$11,G.OCAS!$F$4,F23) -> 0 | E24: =+IF(B24=$I$11,C24*$M$11*D24,IF(B24=$I$12,C24*$M$12*D24,C24*D24)) -> 0 | F24: =+D24+E24 -> 0 | G24: Certificación DANE 102294
... B31: 2000 | C31: 0.0936 | D31: =+IF(B31='REAJUST FISCAL'!$I$11,G.OCAS!$F$4,F30) -> 0 | E31: =+IF(B31=$I$11,C31*$M$11*D31,IF(B31=$I$12,C31*$M$12*D31,C31*D31)) -> 0 | F31: =+D31+E31 -> 0 | G31: Decreto 0333 de 2001
B32: 2001 | C32: 0.0896 | D32: =+IF(B32='REAJUST FISCAL'!$I$11,G.OCAS!$F$4,F31) -> 0 | E32: =+IF(B32=$I$11,C32*$M$11*D32,IF(B32=$I$12,C32*$M$12*D32,C32*D32)) -> 0 | F32: =+D32+E32 -> 0 | G32: Decreto 00406 de 2002 | I32: =+D32*C32 -> 0
B33: 2002 | C33: 0.06 | D33: =+IF(B33='REAJUST FISCAL'!$I$11,G.OCAS!$F$4,F32) -> 0 | E33: =+IF(B33=$I$11,C33*$M$11*D33,IF(B33=$I$12,C33*$M$12*D33,C33*D33)) -> 0 | F33: =+D33+E33 -> 0 | G33: Decreto 3257 de 2002 | I33: =+D33*C33 -> 0
B34: 2003 | C34: 0.06 | D34: =+IF(B34='REAJUST FISCAL'!$I$11,G.OCAS!$F$4,F33) -> 0 | E34: =+IF(B34=$I$11,C34*$M$11*D34,IF(B34=$I$12,C34*$M$12*D34,C34*D34)) -> 0 | F34: =+D34+E34 -> 0 | G34: Decreto 03804 de 2003 | I34: =+D34*C34 -> 0
B35: 2004 | C35: 0.0695 | D35: =+IF(B35='REAJUST FISCAL'!$I$11,G.OCAS!$F$4,F34) -> 0 | E35: =+IF(B35=$I$11,C35*$M$11*D35,IF(B35=$I$12,C35*$M$12*D35,C35*D35)) -> 0 | F35: =+D35+E35 -> 0 | G35: Decreto 4344 de 2003 | I35: =+D35*C35 -> 0
B36: 2005 | C36: 0.061 | D36: =+IF(B36='REAJUST FISCAL'!$I$11,G.OCAS!$F$4,F35) -> 0 | E36: =+IF(B36=$I$11,C36*$M$11*D36,IF(B36=$I$12,C36*$M$12*D36,C36*D36)) -> 0 | F36: =+D36+E36 -> 0 | G36: Decreto 4715 de 2005 | I36: =+D36*C36 -> 0
B37: 2006 | C37: 0.0487 | D37: =+IF(B37='REAJUST FISCAL'!$I$11,G.OCAS!$F$4,F36) -> 0 | E37: =+IF(B37=$I$11,C37*$M$11*D37,IF(B37=$I$12,C37*$M$12*D37,C37*D37)) -> 0 | F37: =+D37+E37 -> 0 | G37: Res. 15652 de 2006 | I37: =+D37*C37 -> 0
B38: 2007 | C38: 0.0515 | D38: =+IF(B38='REAJUST FISCAL'!$I$11,G.OCAS!$F$4,F37) -> 0 | E38: =+IF(B38=$I$11,C38*$M$11*D38,IF(B38=$I$12,C38*$M$12*D38,C38*D38)) -> 0 | F38: =+D38+E38 -> 0 | G38: Res. 15013 de 2007 | I38: =+D38*C38 -> 0
B39: 2008 | C39: 0.0775 | D39: =+IF(B39='REAJUST FISCAL'!$I$11,G.OCAS!$F$4,F38) -> 0 | E39: =+IF(B39=$I$11,C39*$M$11*D39,IF(B39=$I$12,C39*$M$12*D39,C39*D39)) -> 0 | F39: =+D39+E39 -> 0 | G39: Decreto 4715 de 2008
B40: 2009 | C40: 0.0333 | D40: =+IF(B40='REAJUST FISCAL'!$I$11,G.OCAS!$F$4,F39) -> 0 | E40: =+IF(B40=$I$11,C40*$M$11*D40,IF(B40=$I$12,C40*$M$12*D40,C40*D40)) -> 0 | F40: =+D40+E40 -> 0 | G40: Decreto 4930 de 2009 | I40: =+D40*C40 -> 0
B41: 2010 | C41: 0.0235 | D41: =+IF(B41='REAJUST FISCAL'!$I$11,G.OCAS!$F$4,F40) -> 0 | E41: =+IF(B41=$I$11,C41*$M$11*D41,IF(B41=$I$12,C41*$M$12*D41,C41*D41)) -> 0 | F41: =+D41+E41 -> 0 | G41: Decreto 4837 de 2010 | I41: =+D41*C41 -> 0
B42: 2011 | C42: 0.0365 | D42: =+IF(B42='REAJUST FISCAL'!$I$11,G.OCAS!$F$4,F41) -> 0 | E42: =+IF(B42=$I$11,C42*$M$11*D42,IF(B42=$I$12,C42*$M$12*D42,C42*D42)) -> 0 | F42: =+D42+E42 -> 0 | G42: Decreto 4908 de 2011 | I42: =+D42*C42 -> 0
B43: 2012 | C43: 0.0304 | D43: =+IF(B43='REAJUST FISCAL'!$I$11,G.OCAS!$F$4,F42) -> 0 | E43: =+IF(B43=$I$11,C43*$M$11*D43,IF(B43=$I$12,C43*$M$12*D43,C43*D43)) -> 0 | F43: =+D43+E43 -> 0 | G43: Decreto 2714 de 2012 | I43: =+D43*C43 -> 0
B44: 2013 | C44: 0.024 | D44: =+IF(B44='REAJUST FISCAL'!$I$11,G.OCAS!$F$4,F43) -> 0 | E44: =+IF(B44=$I$11,C44*$M$11*D44,IF(B44=$I$12,C44*$M$12*D44,C44*D44)) -> 0 | F44: =+D44+E44 -> 0 | G44: Decreto 2921 de 2013 | I44: =+D44*C44 -> 0
B45: 2014 | C45: 0.0289 | D45: =+IF(B45='REAJUST FISCAL'!$I$11,G.OCAS!$F$4,F44) -> 305000000 | E45: =+IF(B45=$I$11,C45*$M$11*D45,IF(B45=$I$12,C45*$M$12*D45,C45*D45)) -> 1101812.5 | F45: =+D45+E45 -> 3.0610181e+08 | G45: Decreto 2624 de 2014 | I45: =+D45*C45 -> 8814500
B46: 2015 | C46: 0.0521 | D46: =+IF(B46='REAJUST FISCAL'!$I$11,G.OCAS!$F$4,F45) -> 3.0610181e+08 | E46: =+IF(B46=$I$11,C46*$M$11*D46,IF(B46=$I$12,C46*$M$12*D46,C46*D46)) -> 15947904 | F46: =+D46+E46 -> 3.2204972e+08 | G46: Decreto 2453 de 2015 | I46: =+D46*C46 -> 15947904
B47: 2016 | C47: 0.0708 | D47: =+IF(B47='REAJUST FISCAL'!$I$11,G.OCAS!$F$4,F46) -> 3.2204972e+08 | E47: =+IF(B47=$I$11,C47*$M$11*D47,IF(B47=$I$12,C47*$M$12*D47,C47*D47)) -> 22801120 | F47: =+D47+E47 -> 3.4485084e+08 | G47: Decreto 2202 de 2016 | I47: =+D47*C47 -> 22801120
B48: 2017 | C48: 0.0407 | D48: =+IF(B48='REAJUST FISCAL'!$I$11,G.OCAS!$F$4,F47) -> 3.4485084e+08 | E48: =+IF(B48=$I$11,C48*$M$11*D48,IF(B48=$I$12,C48*$M$12*D48,C48*D48)) -> 14035429 | F48: =+D48+E48 -> 3.5888627e+08 | G48: Decreto 2169 de 2017 | I48: =+D48*C48 -> 14035429
B49: 2018 | C49: 0.0407 | D49: =+IF(B49='REAJUST FISCAL'!$I$11,G.OCAS!$F$4,F48) -> 3.5888627e+08 | E49: =+IF(B49=$I$11,C49*$M$11*D49,IF(B49=$I$12,C49*$M$12*D49,C49*D49)) -> 14606671 | F49: =+D49+E49 -> 3.7349294e+08 | G49: Decreto 2391 de 2018 | I49: =+D49*C49 -> 14606671
B50: 2019 | C50: 0.0336 | D50: =+IF(B50='REAJUST FISCAL'!$I$11,G.OCAS!$F$4,F49) -> 3.7349294e+08 | E50: =+IF(B50=$I$11,C50*$M$11*D50,IF(B50=$I$12,C50*$M$12*D50,C50*D50)) -> 12549363 | F50: =+D50+E50 -> 3.860423e+08 | G50: Decreto 2373 de 2019 | I50: =+D50*C50 -> 12549363
B51: 2020 | C51: 0.039 | D51: =+IF(B51='REAJUST FISCAL'!$I$11,G.OCAS!$F$4,F50) -> 3.860423e+08 | E51: =+IF(B51=$I$11,C51*$M$11*D51,IF(B51=$I$12,C51*$M$12*D51,C51*D51)) -> 15055650 | F51: =+D51+E51 -> 4.0109795e+08 | G51: Decreto 1763 de 2020 | I51: =+D51*C51 -> 15055650
... B55: 2024 | C55: 0.1097 | D55: =+IF(B55='REAJUST FISCAL'!$I$11,G.OCAS!$F$4,F54) -> 4.8118424e+08 | E55: =+IF(B55=$I$11,C55*$M$11*D55,IF(B55=$I$12,C55*$M$12*D55,C55*D55)) -> 52785911 | F55: =+D55+E55 -> 5.3397015e+08 | G55: Decreto 174 de 2025 | I55: =+D55*C55 -> 52785911
B56: 2025 | C56: 0.0581 | D56: =+IF(B56='REAJUST FISCAL'!$I$11,G.OCAS!$F$4,F55) -> 5.3397015e+08 | E56: =+IF(B56=$I$11,C56*$M$11*D56,IF(B56=$I$12,C56*$M$12*D56,C56*D56)) -> 47052560 | F56: =+D56+E56 -> 5.8102271e+08 | G56: Decreto 0049 de 2026
B57: TOTAL REAJUSTE | F57: =F56 -> 5.8102271e+08
B64: AÑO | C64: % | D64: VALOR BASE | E64: REAJUSTE | F64: TOTAL REAJUSTADO | G64: Normatividad
B65: 1974 | C65: 0.08 | D65: =+IF(B65='REAJUST FISCAL'!$I$69,G.OCAS!$F$4,0) -> 0 | E65: =+IF(B65=$I$69,C65*$M$69*D65,IF(B65=$I$70,C65*$M$70*D65,C65*D65)) -> 0 | F65: =+'REAJUST FISCAL'!D65+E65 -> 0 | G65: Decreto 2247 de 1974
B66: 1975 | C66: 0.08 | D66: =+IF('REAJUST FISCAL'!B66='REAJUST FISCAL'!$I$69,G.OCAS!$F$18,'REAJUST FISCAL'!F65) -> 0 | E66: =+IF(B66=$I$69,C66*$M$69*D66,IF(B66=$I$70,C66*$M$70*D66,C66*D66)) -> 0 | F66: =+D66+E66 -> 0 | G66: Decreto 187 de 1975
B67: 1976 | C67: 0.08 | D67: =+IF('REAJUST FISCAL'!B67='REAJUST FISCAL'!$I$69,G.OCAS!$F$18,'REAJUST FISCAL'!F66) -> 0 | E67: =+IF(B67=$I$69,C67*$M$69*D67,IF(B67=$I$70,C67*$M$70*D67,C67*D67)) -> 0 | F67: =+D67+E67 -> 0 | G67: Ley 19 de 1976
B68: 1977 | C68: 0.14 | D68: =+IF('REAJUST FISCAL'!B68='REAJUST FISCAL'!$I$69,G.OCAS!$F$18,'REAJUST FISCAL'!F67) -> 0 | E68: =+IF(B68=$I$69,C68*$M$69*D68,IF(B68=$I$70,C68*$M$70*D68,C68*D68)) -> 0 | F68: =+D68+E68 -> 0 | G68: Ley 54 de 1977
B69: 1978 | C69: 0.095 | D69: =+IF('REAJUST FISCAL'!B69='REAJUST FISCAL'!$I$69,G.OCAS!$F$18,'REAJUST FISCAL'!F68) -> 0 | E69: =+IF(B69=$I$69,C69*$M$69*D69,IF(B69=$I$70,C69*$M$70*D69,C69*D69)) -> 0 | F69: =+D69+E69 -> 0 | G69: Decreto 2114 de 1978 | I69: =+YEAR(G.OCAS!F19) -> 2021 | J69: =+CONCATENATE("31/12/",+I69) -> 31/12/2021 | K69: 360 | L69: =+_xlfn.DAYS(J69,G.OCAS!F19) -> 169 | M69: =+L69/K69 -> 0.46944444 | N69: =+M69*'REAJUST FISCAL'!C110 -> 0.015773333
B70: 1979 | C70: 0.244 | D70: =+IF('REAJUST FISCAL'!B70='REAJUST FISCAL'!$I$69,G.OCAS!$F$18,'REAJUST FISCAL'!F69) -> 0 | E70: =+IF(B70=$I$69,C70*$M$69*D70,IF(B70=$I$70,C70*$M$70*D70,C70*D70)) -> 0 | F70: =+D70+E70 -> 0 | G70: Ley 20 de 1979 /Decreto 2326 de 1979 | I70: =+YEAR(G.OCAS!F20) -> 2025 | J70: 45292 | K70: 360 | L70: =+_xlfn.DAYS(G.OCAS!F20,J70) -> 564 | M70: =+L70/K70 -> 1.5666667
B71: 1980 | C71: 0.2472 | D71: =+IF('REAJUST FISCAL'!B71='REAJUST FISCAL'!$I$69,G.OCAS!$F$18,'REAJUST FISCAL'!F70) -> 0 | E71: =+IF(B71=$I$69,C71*$M$69*D71,IF(B71=$I$70,C71*$M$70*D71,C71*D71)) -> 0 | F71: =+D71+E71 -> 0 | G71: Decreto 2534 de 1980
B72: 1981 | C72: 0.2775 | D72: =+IF('REAJUST FISCAL'!B72='REAJUST FISCAL'!$I$69,G.OCAS!$F$18,'REAJUST FISCAL'!F71) -> 0 | E72: =+IF(B72=$I$69,C72*$M$69*D72,IF(B72=$I$70,C72*$M$70*D72,C72*D72)) -> 0 | F72: =+D72+E72 -> 0 | G72: Decreto 2655 de 1981
B73: 1982 | C73: 0.2347 | D73: =+IF('REAJUST FISCAL'!B73='REAJUST FISCAL'!$I$69,G.OCAS!$F$18,'REAJUST FISCAL'!F72) -> 0 | E73: =+IF(B73=$I$69,C73*$M$69*D73,IF(B73=$I$70,C73*$M$70*D73,C73*D73)) -> 0 | F73: =+D73+E73 -> 0 | G73: Decreto 2809 de 1982
B74: 1983 | C74: 0.1942 | D74: =+IF('REAJUST FISCAL'!B74='REAJUST FISCAL'!$I$69,G.OCAS!$F$18,'REAJUST FISCAL'!F73) -> 0 | E74: =+IF(B74=$I$69,C74*$M$69*D74,IF(B74=$I$70,C74*$M$70*D74,C74*D74)) -> 0 | F74: =+D74+E74 -> 0 | G74: Ley 9 de 1983/Decreto 2124 de 1983
B75: 1984 | C75: 0.1517 | D75: =+IF('REAJUST FISCAL'!B75='REAJUST FISCAL'!$I$69,G.OCAS!$F$18,'REAJUST FISCAL'!F74) -> 0 | E75: =+IF(B75=$I$69,C75*$M$69*D75,IF(B75=$I$70,C75*$M$70*D75,C75*D75)) -> 0 | F75: =+D75+E75 -> 0 | G75: Decreto 1843 de 1984
B76: 1985 | C76: 0.2451 | D76: =+IF('REAJUST FISCAL'!B76='REAJUST FISCAL'!$I$69,G.OCAS!$F$18,'REAJUST FISCAL'!F75) -> 0 | E76: =+IF(B76=$I$69,C76*$M$69*D76,IF(B76=$I$70,C76*$M$70*D76,C76*D76)) -> 0 | F76: =+D76+E76 -> 0 | G76: Decreto 2032 de 1985
B77: 1986 | C77: 0.163 | D77: =+IF('REAJUST FISCAL'!B77='REAJUST FISCAL'!$I$69,G.OCAS!$F$18,'REAJUST FISCAL'!F76) -> 0 | E77: =+IF(B77=$I$69,C77*$M$69*D77,IF(B77=$I$70,C77*$M$70*D77,C77*D77)) -> 0 | F77: =+D77+E77 -> 0 | G77: Ley 75 de 1986/Decreto 2444 de 1986
B78: 1987 | C78: 0.1679 | D78: =+IF('REAJUST FISCAL'!B78='REAJUST FISCAL'!$I$69,G.OCAS!$F$18,'REAJUST FISCAL'!F77) -> 0 | E78: =+IF(B78=$I$69,C78*$M$69*D78,IF(B78=$I$70,C78*$M$70*D78,C78*D78)) -> 0 | F78: =+D78+E78 -> 0 | G78: Decreto 59 de 1987
B79: 1988 | C79: 0.2365 | D79: =+IF('REAJUST FISCAL'!B79='REAJUST FISCAL'!$I$69,G.OCAS!$F$18,'REAJUST FISCAL'!F78) -> 0 | E79: =+IF(B79=$I$69,C79*$M$69*D79,IF(B79=$I$70,C79*$M$70*D79,C79*D79)) -> 0 | F79: =+D79+E79 -> 0 | G79: Decreto 2540 de 1987
B80: 1989 | C80: 0.2799 | D80: =+IF('REAJUST FISCAL'!B80='REAJUST FISCAL'!$I$69,G.OCAS!$F$18,'REAJUST FISCAL'!F79) -> 0 | E80: =+IF(B80=$I$69,C80*$M$69*D80,IF(B80=$I$70,C80*$M$70*D80,C80*D80)) -> 0 | F80: =+D80+E80 -> 0 | G80: Decreto 2671 de 1988
B81: 1990 | C81: 0.2664 | D81: =+IF('REAJUST FISCAL'!B81='REAJUST FISCAL'!$I$69,G.OCAS!$F$18,'REAJUST FISCAL'!F80) -> 0 | E81: =+IF(B81=$I$69,C81*$M$69*D81,IF(B81=$I$70,C81*$M$70*D81,C81*D81)) -> 0 | F81: =+D81+E81 -> 0 | G81: Decreto 624 de 1989 / Decreto 3018 de 1989
B82: 1991 | C82: 0.3004 | D82: =+IF('REAJUST FISCAL'!B82='REAJUST FISCAL'!$I$69,G.OCAS!$F$18,'REAJUST FISCAL'!F81) -> 0 | E82: =+IF(B82=$I$69,C82*$M$69*D82,IF(B82=$I$70,C82*$M$70*D82,C82*D82)) -> 0 | F82: =+D82+E82 -> 0 | G82: Decreto 3100 de 1990
... B91: 2000 | C91: 0.0936 | D91: =+IF('REAJUST FISCAL'!B91='REAJUST FISCAL'!$I$69,G.OCAS!$F$18,'REAJUST FISCAL'!F90) -> 0 | E91: =+IF(B91=$I$69,C91*$M$69*D91,IF(B91=$I$70,C91*$M$70*D91,C91*D91)) -> 0 | F91: =+D91+E91 -> 0 | G91: Decreto 0333 de 2001
B92: 2001 | C92: 0.0896 | D92: =+IF('REAJUST FISCAL'!B92='REAJUST FISCAL'!$I$69,G.OCAS!$F$18,'REAJUST FISCAL'!F91) -> 0 | E92: =+IF(B92=$I$69,C92*$M$69*D92,IF(B92=$I$70,C92*$M$70*D92,C92*D92)) -> 0 | F92: =+D92+E92 -> 0 | G92: Decreto 00406 de 2002 | I92: =+D92*C92 -> 0
B93: 2002 | C93: 0.06 | D93: =+IF('REAJUST FISCAL'!B93='REAJUST FISCAL'!$I$69,G.OCAS!$F$18,'REAJUST FISCAL'!F92) -> 0 | E93: =+IF(B93=$I$69,C93*$M$69*D93,IF(B93=$I$70,C93*$M$70*D93,C93*D93)) -> 0 | F93: =+D93+E93 -> 0 | G93: Decreto 3257 de 2002 | I93: =+D93*C93 -> 0
B94: 2003 | C94: 0.06 | D94: =+IF('REAJUST FISCAL'!B94='REAJUST FISCAL'!$I$69,G.OCAS!$F$18,'REAJUST FISCAL'!F93) -> 0 | E94: =+IF(B94=$I$69,C94*$M$69*D94,IF(B94=$I$70,C94*$M$70*D94,C94*D94)) -> 0 | F94: =+D94+E94 -> 0 | G94: Decreto 03804 de 2003 | I94: =+D94*C94 -> 0
B95: 2004 | C95: 0.0695 | D95: =+IF('REAJUST FISCAL'!B95='REAJUST FISCAL'!$I$69,G.OCAS!$F$18,'REAJUST FISCAL'!F94) -> 0 | E95: =+IF(B95=$I$69,C95*$M$69*D95,IF(B95=$I$70,C95*$M$70*D95,C95*D95)) -> 0 | F95: =+D95+E95 -> 0 | G95: Decreto 4344 de 2003 | I95: =+D95*C95 -> 0
B96: 2005 | C96: 0.061 | D96: =+IF('REAJUST FISCAL'!B96='REAJUST FISCAL'!$I$69,G.OCAS!$F$18,'REAJUST FISCAL'!F95) -> 0 | E96: =+IF(B96=$I$69,C96*$M$69*D96,IF(B96=$I$70,C96*$M$70*D96,C96*D96)) -> 0 | F96: =+D96+E96 -> 0 | G96: Decreto 4715 de 2005 | I96: =+D96*C96 -> 0
B97: 2006 | C97: 0.0487 | D97: =+IF('REAJUST FISCAL'!B97='REAJUST FISCAL'!$I$69,G.OCAS!$F$18,'REAJUST FISCAL'!F96) -> 0 | E97: =+IF(B97=$I$69,C97*$M$69*D97,IF(B97=$I$70,C97*$M$70*D97,C97*D97)) -> 0 | F97: =+D97+E97 -> 0 | G97: Res. 15652 de 2006 | I97: =+D97*C97 -> 0
B98: 2007 | C98: 0.0515 | D98: =+IF('REAJUST FISCAL'!B98='REAJUST FISCAL'!$I$69,G.OCAS!$F$18,'REAJUST FISCAL'!F97) -> 0 | E98: =+IF(B98=$I$69,C98*$M$69*D98,IF(B98=$I$70,C98*$M$70*D98,C98*D98)) -> 0 | F98: =+D98+E98 -> 0 | G98: Res. 15013 de 2007 | I98: =+D98*C98 -> 0
B99: 2008 | C99: 0.0775 | D99: =+IF('REAJUST FISCAL'!B99='REAJUST FISCAL'!$I$69,G.OCAS!$F$18,'REAJUST FISCAL'!F98) -> 0 | E99: =+IF(B99=$I$69,C99*$M$69*D99,IF(B99=$I$70,C99*$M$70*D99,C99*D99)) -> 0 | F99: =+D99+E99 -> 0 | G99: Decreto 4715 de 2008
B100: 2009 | C100: 0.0333 | D100: =+IF('REAJUST FISCAL'!B100='REAJUST FISCAL'!$I$69,G.OCAS!$F$18,'REAJUST FISCAL'!F99) -> 0 | E100: =+IF(B100=$I$69,C100*$M$69*D100,IF(B100=$I$70,C100*$M$70*D100,C100*D100)) -> 0 | F100: =+D100+E100 -> 0 | G100: Decreto 4930 de 2009 | I100: =+D100*C100 -> 0
B101: 2010 | C101: 0.0235 | D101: =+IF('REAJUST FISCAL'!B101='REAJUST FISCAL'!$I$69,G.OCAS!$F$18,'REAJUST FISCAL'!F100) -> 0 | E101: =+IF(B101=$I$69,C101*$M$69*D101,IF(B101=$I$70,C101*$M$70*D101,C101*D101)) -> 0 | F101: =+D101+E101 -> 0 | G101: Decreto 4837 de 2010 | I101: =+D101*C101 -> 0
B102: 2011 | C102: 0.0365 | D102: =+IF('REAJUST FISCAL'!B102='REAJUST FISCAL'!$I$69,G.OCAS!$F$18,'REAJUST FISCAL'!F101) -> 0 | E102: =+IF(B102=$I$69,C102*$M$69*D102,IF(B102=$I$70,C102*$M$70*D102,C102*D102)) -> 0 | F102: =+'REAJUST FISCAL'!D102+E102 -> 0 | G102: Decreto 4908 de 2011 | I102: =+'REAJUST FISCAL'!D102*C102 -> 0
B103: 2012 | C103: 0.0304 | D103: =+IF('REAJUST FISCAL'!B103='REAJUST FISCAL'!$I$69,G.OCAS!$F$18,'REAJUST FISCAL'!F102) -> 0 | E103: =+IF(B103=$I$69,C103*$M$69*D103,IF(B103=$I$70,C103*$M$70*D103,C103*D103)) -> 0 | F103: =+D103+E103 -> 0 | G103: Decreto 2714 de 2012 | I103: =+D103*C103 -> 0
B104: 2013 | C104: 0.024 | D104: =+IF('REAJUST FISCAL'!B104='REAJUST FISCAL'!$I$69,G.OCAS!$F$18,'REAJUST FISCAL'!F103) -> 0 | E104: =+IF(B104=$I$69,C104*$M$69*D104,IF(B104=$I$70,C104*$M$70*D104,C104*D104)) -> 0 | F104: =+D104+E104 -> 0 | G104: Decreto 2921 de 2013 | I104: =+D104*C104 -> 0
B105: 2014 | C105: 0.0289 | D105: =+IF('REAJUST FISCAL'!B105='REAJUST FISCAL'!$I$69,G.OCAS!$F$18,'REAJUST FISCAL'!F104) -> 0 | E105: =+IF(B105=$I$69,C105*$M$69*D105,IF(B105=$I$70,C105*$M$70*D105,C105*D105)) -> 0 | F105: =+D105+E105 -> 0 | G105: Decreto 2624 de 2014 | I105: =+D105*C105 -> 0
B106: 2015 | C106: 0.0521 | D106: =+IF('REAJUST FISCAL'!B106='REAJUST FISCAL'!$I$69,G.OCAS!$F$18,'REAJUST FISCAL'!F105) -> 0 | E106: =+IF(B106=$I$69,C106*$M$69*D106,IF(B106=$I$70,C106*$M$70*D106,C106*D106)) -> 0 | F106: =+D106+E106 -> 0 | G106: Decreto 2453 de 2015 | I106: =+D106*C106 -> 0
B107: 2016 | C107: 0.0708 | D107: =+IF('REAJUST FISCAL'!B107='REAJUST FISCAL'!$I$69,G.OCAS!$F$18,'REAJUST FISCAL'!F106) -> 0 | E107: =+IF(B107=$I$69,C107*$M$69*D107,IF(B107=$I$70,C107*$M$70*D107,C107*D107)) -> 0 | F107: =+D107+E107 -> 0 | G107: Decreto 2202 de 2016 | I107: =+D107*C107 -> 0
B108: 2017 | C108: 0.0407 | D108: =+IF('REAJUST FISCAL'!B108='REAJUST FISCAL'!$I$69,G.OCAS!$F$18,'REAJUST FISCAL'!F107) -> 0 | E108: =+IF(B108=$I$69,C108*$M$69*D108,IF(B108=$I$70,C108*$M$70*D108,C108*D108)) -> 0 | F108: =+D108+E108 -> 0 | G108: Decreto 2169 de 2017 | I108: =+D108*C108 -> 0
B109: 2018 | C109: 0.0407 | D109: =+IF('REAJUST FISCAL'!B109='REAJUST FISCAL'!$I$69,G.OCAS!$F$18,'REAJUST FISCAL'!F108) -> 0 | E109: =+IF(B109=$I$69,C109*$M$69*D109,IF(B109=$I$70,C109*$M$70*D109,C109*D109)) -> 0 | F109: =+D109+E109 -> 0 | G109: Decreto 2391 de 2018 | I109: =+D109*C109 -> 0
B110: 2019 | C110: 0.0336 | D110: =+IF('REAJUST FISCAL'!B110='REAJUST FISCAL'!$I$69,G.OCAS!$F$18,'REAJUST FISCAL'!F109) -> 0 | E110: =+IF(B110=$I$69,C110*$M$69*D110,IF(B110=$I$70,C110*$M$70*D110,C110*D110)) -> 0 | F110: =+D110+E110 -> 0 | G110: Decreto 2373 de 2019 | I110: =+D110*C110 -> 0
B111: 2020 | C111: 0.039 | D111: =+IF('REAJUST FISCAL'!B111='REAJUST FISCAL'!$I$69,G.OCAS!$F$18,'REAJUST FISCAL'!F110) -> 0 | E111: =+IF(B111=$I$69,C111*$M$69*'REAJUST FISCAL'!D111,IF(B111=$I$70,C111*$M$70*'REAJUST FISCAL'!D111,C111*'REAJUST FISCAL'!D111)) -> 0 | F111: =+'REAJUST FISCAL'!D111+E111 -> 0 | G111: Decreto 1763 de 2020 | I111: =+'REAJUST FISCAL'!D111*C111 -> 0
B112: 2021 | C112: 0.0197 | D112: =+IF('REAJUST FISCAL'!B112='REAJUST FISCAL'!$I$69,G.OCAS!$F$18,'REAJUST FISCAL'!F111) -> 150000000 | E112: =+IF(B112=$I$69,C112*$M$69*D112,IF(B112=$I$70,C112*$M$70*D112,C112*D112)) -> 1387208.3 | F112: =+D112+E112 -> 1.5138721e+08 | G112: Decreto 1846 de 2021 | I112: =+D112*C112 -> 2955000
B113: 2022 | C113: 0.0467 | D113: =+IF('REAJUST FISCAL'!B113='REAJUST FISCAL'!$I$69,G.OCAS!$F$18,'REAJUST FISCAL'!F112) -> 1.5138721e+08 | E113: =+IF(B113=$I$69,C113*$M$69*D113,IF(B113=$I$70,C113*$M$70*D113,C113*D113)) -> 7069782.6 | F113: =+D113+E113 -> 1.5845699e+08 | G113: Decreto 2609 de 2022 | I113: =+D113*C113 -> 7069782.6
B114: 2023 | C114: 0.124 | D114: =+IF('REAJUST FISCAL'!B114='REAJUST FISCAL'!$I$69,G.OCAS!$F$18,'REAJUST FISCAL'!F113) -> 1.5845699e+08 | E114: =+IF(B114=$I$69,C114*$M$69*D114,IF(B114=$I$70,C114*$M$70*D114,C114*D114)) -> 19648667 | F114: =+D114+E114 -> 1.7810566e+08 | G114: Decreto 128 de 2024 | I114: =+D114*C114 -> 19648667
B115: 2024 | C115: 0.1097 | D115: =+IF('REAJUST FISCAL'!B115='REAJUST FISCAL'!$I$69,G.OCAS!$F$18,'REAJUST FISCAL'!F114) -> 1.7810566e+08 | E115: =+IF(B115=$I$69,C115*$M$69*D115,IF(B115=$I$70,C115*$M$70*D115,C115*D115)) -> 19538191 | F115: =+D115+E115 -> 1.9764385e+08 | G115: Decreto 174 de 2025 | I115: =+D115*C115 -> 19538191
B116: 2025 | C116: 0.0581 | D116: =+IF('REAJUST FISCAL'!B116='REAJUST FISCAL'!$I$69,G.OCAS!$F$18,'REAJUST FISCAL'!F115) -> 1.9764385e+08 | E116: =+IF(B116=$I$69,C116*$M$69*D116,IF(B116=$I$70,C116*$M$70*D116,C116*D116)) -> 17990202 | F116: =+D116+E116 -> 2.1563405e+08 | G116: Decreto 0049 de 2026
B117: TOTAL REAJUSTE | F117: =F116 -> 2.1563405e+08
B126: AÑO | C126: % | D126: VALOR BASE | E126: REAJUSTE | F126: TOTAL REAJUSTADO | G126: Normatividad
B127: 1974 | C127: 0.08 | D127: =+IF('REAJUST FISCAL'!B127='REAJUST FISCAL'!$I$69,G.OCAS!$F$31,0) -> 0 | E127: =+IF(B127=$I$139,C127*$M$139*'REAJUST FISCAL'!D127,IF(B127=$I$140,C127*$M$140*'REAJUST FISCAL'!D127,C127*'REAJUST FISCAL'!D127)) -> 0 | F127: =+'REAJUST FISCAL'!D127+E127 -> 0 | G127: Decreto 2247 de 1974
B128: 1975 | C128: 0.08 | D128: =+IF('REAJUST FISCAL'!B128='REAJUST FISCAL'!$I$139,G.OCAS!$F$32,'REAJUST FISCAL'!F127) -> 0 | E128: =+IF(B128=$I$139,C128*$M$139*'REAJUST FISCAL'!D128,IF(B128=$I$140,C128*$M$140*'REAJUST FISCAL'!D128,C128*'REAJUST FISCAL'!D128)) -> 0 | F128: =+'REAJUST FISCAL'!D128+E128 -> 0 | G128: Decreto 187 de 1975
B129: 1976 | C129: 0.08 | D129: =+IF('REAJUST FISCAL'!B129='REAJUST FISCAL'!$I$139,G.OCAS!$F$32,'REAJUST FISCAL'!F128) -> 0 | E129: =+IF(B129=$I$139,C129*$M$139*'REAJUST FISCAL'!D129,IF(B129=$I$140,C129*$M$140*'REAJUST FISCAL'!D129,C129*'REAJUST FISCAL'!D129)) -> 0 | F129: =+D129+E129 -> 0 | G129: Ley 19 de 1976
B130: 1977 | C130: 0.14 | D130: =+IF('REAJUST FISCAL'!B130='REAJUST FISCAL'!$I$139,G.OCAS!$F$32,'REAJUST FISCAL'!F129) -> 0 | E130: =+IF(B130=$I$139,C130*$M$139*'REAJUST FISCAL'!D130,IF(B130=$I$140,C130*$M$140*'REAJUST FISCAL'!D130,C130*'REAJUST FISCAL'!D130)) -> 0 | F130: =+D130+E130 -> 0 | G130: Ley 54 de 1977
B131: 1978 | C131: 0.095 | D131: =+IF('REAJUST FISCAL'!B131='REAJUST FISCAL'!$I$139,G.OCAS!$F$32,'REAJUST FISCAL'!F130) -> 0 | E131: =+IF(B131=$I$139,C131*$M$139*'REAJUST FISCAL'!D131,IF(B131=$I$140,C131*$M$140*'REAJUST FISCAL'!D131,C131*'REAJUST FISCAL'!D131)) -> 0 | F131: =+D131+E131 -> 0 | G131: Decreto 2114 de 1978
B132: 1979 | C132: 0.244 | D132: =+IF('REAJUST FISCAL'!B132='REAJUST FISCAL'!$I$139,G.OCAS!$F$32,'REAJUST FISCAL'!F131) -> 0 | E132: =+IF(B132=$I$139,C132*$M$139*'REAJUST FISCAL'!D132,IF(B132=$I$140,C132*$M$140*'REAJUST FISCAL'!D132,C132*'REAJUST FISCAL'!D132)) -> 0 | F132: =+D132+E132 -> 0 | G132: Ley 20 de 1979 /Decreto 2326 de 1979
B133: 1980 | C133: 0.2472 | D133: =+IF('REAJUST FISCAL'!B133='REAJUST FISCAL'!$I$139,G.OCAS!$F$32,'REAJUST FISCAL'!F132) -> 0 | E133: =+IF(B133=$I$139,C133*$M$139*'REAJUST FISCAL'!D133,IF(B133=$I$140,C133*$M$140*'REAJUST FISCAL'!D133,C133*'REAJUST FISCAL'!D133)) -> 0 | F133: =+D133+E133 -> 0 | G133: Decreto 2534 de 1980
B134: 1981 | C134: 0.2775 | D134: =+IF('REAJUST FISCAL'!B134='REAJUST FISCAL'!$I$139,G.OCAS!$F$32,'REAJUST FISCAL'!F133) -> 0 | E134: =+IF(B134=$I$139,C134*$M$139*'REAJUST FISCAL'!D134,IF(B134=$I$140,C134*$M$140*'REAJUST FISCAL'!D134,C134*'REAJUST FISCAL'!D134)) -> 0 | F134: =+D134+E134 -> 0 | G134: Decreto 2655 de 1981
...

Sheet C.pensiones
B1: RENTAS DE PENSIONES
B2: Renglón 99 | C2: De fuente nacional y de fuente extranjera | F2: =ROUND(SUM(E9+E16),-3) -> 0
C3: Porvenir
C4: Colpensiones
C5: Estados Unidos
C6: Indemnizacion sustitutiva o devolucion de saldos
C9: Total ingresos por pensiones - fuente nacional | E9: =SUM(E3:E8) -> 0
C10: De fuente extranjera
E13: 0
C16: Total ingresos por pensiones - fuente extranjera | E16: =SUM(E11:E15) -> 0
B17: Renglón 100 | C17: I.N.C.R.N.G.O.
F18: =ROUND(SUM(E18:E24),-3) -> 0
C19: aporte a salud
B25: Renglón 102 | C25: Rentas exentas
C26: Renta exenta pensinoes de Colombia de fuente Nacional | E26: =E3-E18 -> 0 | F26: =IF(E9>0,E9-F18,0) -> 0

Sheet renta presunt
B2: RENTA PRESUNTIVA
B4: Total patrimonio bruto 2024 | E4: 3430000000
B5: Deudas | E5: 360000000
B6: Patrimonio líquido 2024 | E6: =(E4-E5) -> 3070000000
B7: Menos: patrimonio excluido
B8: % Valor Patrimonial | E8: =IFERROR(E6/E4,0) -> 0.89504373
B9: V/r. de las acciones en sociedades nacionales | D9: 0 | E9: =D9*$E$8 -> 0
B10: V/r. del total de los activos destinados a empresas en periodo improductivo | D10: 0 | E10: =D10*$E$8 -> 0
B11: V/r. de los activos afectados por fuerza mayor o caso fortuito | D11: 0 | E11: =D11*$E$8 -> 0
B12: Las primeras 8.000 UVT Casa habitación | D12: 0 | E12: =IF(D12>265248000,265248000,D12) -> 0
B13: Las primeras 19.000 UVT activos destinados sector agropecuario | E13: =IF(D13>605321000,605321000,D13) -> 0
B14: Total base renta presuntiva | E14: =E6-E9-E12 -> 3070000000
B15: Renta presuntiva Inicial | D15: 0 | E15: =ROUND((E14*D15),-3) -> 0
B16: Más: ingresos gravados generados por los activos excluídos - Divid. gravados | E16: 0
B17: Total renta presuntiva depurada | E17: =ROUND(SUM(E15:E16),-3) -> 0

Sheet C divid.
B1: RENTAS POR DIVIDENDOS Y PARTICIPACIONES
B2: Renglon 104 | C2: Dividendos y participaciones 2016, anteriores y otros
F3: =ROUND(SUM(E3:E9),-3) -> 59000000
C4: Dividendos no gravados | E4: 34000000
C5: Dividendos gravados | E5: 25000000
B10: Renglon 105 | C10: I.N.C.R.N.G.O.
F11: =ROUND(SUM(E11:E15),-3) -> 34000000
C12: Dividendos no gravados | E12: =E4 -> 34000000
B16: Renglon 107 | C16: 1a. Subcédula año 2017 y siguientes numeral 3. Art 49 del E.T.
F17: =ROUND(SUM(E17:E23),-3) -> 50000000
C18: Dividendos no gravados | E18: 50000000
B24: Renglon 108 | C24: 2a Subcedula año 2017 y siguientes (parágrafo 2 Art. 49)
F25: =ROUND(SUM(E25:E31),-3) -> 43000000
C26: Dividendos gravados | E26: 43000000
B32: Renglon 109 | C32: Renta líquida pasiva dividendos - E.C.E.
F33: =ROUND(SUM(E33:E39),-3) -> 0
B40: Renglon 110 | C40: Rentas exentas de la casilla 110
F41: =ROUND(SUM(E41:E47),-3) -> 0

Sheet impto renta
A2: Valor UVT año 2023 | E2: 47065 | H2: R.L.C.GENERAL | I2: ='FORMULARIO 210'!J46 -> 432584000
H3: Renta presuntiva | I3: ='FORMULARIO 210'!AA33 -> 0
H4: Renta liq pension | I4: ='FORMULARIO 210'!J38 -> 0
H5: Total | I5: =SUM(I3:I4) -> 0
A7: Ingresos brutos anuales | C7: Ingresos brutos anuales | E7: Tarifa marginal | F7: CALCULO | G7: BASE CEDULA GENERAL Y PENSIÓN | H7: IMPUESTO | I7: BASE RENTA PRESUNTIVA Y PENSIÓN | J7: IMPUESTO
A8: Igual o superior | B8: Igual o superior | C8: Inferior
A9: 0 | B9: 1090 | C9: =A9*$E$2 -> 0 | D9: =B9*$E$2 -> 51300850 | E9: 0 | F9: 0 | G9: ='FORMULARIO 210'!J46 -> 432584000 | H9: 0 | I9: =IF(I5>I2,I5,0) -> 0 | J9: 0
A10: =B9+1 -> 1091 | B10: 1700 | C10: =A10*$E$2 -> 51347915 | D10: =B10*$E$2 -> 80010500 | E10: 0.19 | F10: (Base gravable en UVT Menos 1090 UVT) *19% | G10: =$G$9 -> 432584000 | H10: =(((G10/$E$2)-1090)*19%)*E2 -> 72443799 | I10: =$I$9 -> 0 | J10: =(((I10/$E$2)-1090)*19%)*E2 -> -9747161.5
A11: =B10+1 -> 1701 | B11: 4100 | C11: =A11*$E$2 -> 80057565 | D11: =B11*$E$2 -> 192966500 | E11: 0.28 | F11: (Base gravable en UVT Menos 1700 UVT) *28% + 116 UVT | G11: =$G$9 -> 432584000 | H11: =((((G11/$E$2)-1700)*28%)+116)*$E$2 -> 104180120 | I11: =$I$9 -> 0 | J11: =((((I11/$E$2)-1700)*28%)+116)*$E$2 -> -16943400
A12: =B11+1 -> 4101 | B12: 8670 | C12: =A12*$E$2 -> 193013565 | D12: =B12*$E$2 -> 408053550 | E12: 0.33 | F12: (Base gravable en UVT Menos 4100 UVT) *33% + 788 UVT | G12: =$G$9 -> 432584000 | H12: =((((G12/$E$2)-4100)*33%)+788)*$E$2 -> 1.16161e+08 | I12: =$I$9 -> 0 | J12: =((((I12/$E$2)-4100)*33%)+788)*$E$2 -> -26591725
A13: =B12+1 -> 8671 | B13: 18970 | C13: =A13*$E$2 -> 408100615 | D13: =B13*$E$2 -> 892823050 | E13: 0.35 | F13: (Base gravable en UVT Menos 8670 UVT) *35% + 2296 UVT | G13: =$G$9 -> 432584000 | H13: =((((G13/$E$2)-8670)*35%)+2296)*$E$2 -> 1.166469e+08 | I13: =$I$9 -> 0 | J13: =((((I13/$E$2)-8670)*35%)+2296)*$E$2 -> -34757502
A14: =B13+1 -> 18971 | B14: 31000 | C14: =A14*$E$2 -> 892870115 | D14: =B14*$E$2 -> 1459015000 | E14: 0.37 | F14: (Base gravable en UVT Menos 18970 UVT) *37% + 5901 UVT | G14: =$G$9 -> 432584000 | H14: =((((G14/$E$2)-18970)*37%)+5901)*$E$2 -> 1.0744212e+08 | I14: =$I$9 -> 0 | J14: =((((I14/$E$2)-18970)*37%)+5901)*$E$2 -> -52613963
A15: =B14+1 -> 31001 | B15: En adelante | C15: =A15*$E$2 -> 1459062065 | D15: 9999999999 | E15: 0.39 | F15: (Base gravable en UVT Menos 31000 UVT) *39% - 10352 UVT | G15: =$G$9 -> 432584000 | H15: =((((G15/$E$2)-31000)*39%)+10352)*$E$2 -> 86908790 | I15: =$I$9 -> 0 | J15: =((((I15/$E$2)-31000)*39%)+10352)*$E$2 -> -81798970
A17: Renta cedula general + pensión | E17: =ROUND(IF(AND('impto renta'!G9>'impto renta'!C9,'impto renta'!G9<'impto renta'!D9),'impto renta'!H9,IF(AND('impto renta'!G10>'impto renta'!C10,'impto renta'!G10<'impto renta'!D10),'impto renta'!H10,IF(AND('impto renta'!G11>'impto renta'!C11,'impto renta'!G11<'impto renta'!D11),'impto renta'!H11,IF(AND('impto renta'!G12>'impto renta'!C12,'impto renta'!G12<'impto renta'!D12),'impto renta'!H12,IF(AND('impto renta'!G13>'impto renta'!C13,'impto renta'!G13<'impto renta'!D13),'impto renta'!H13,IF(AND('impto renta'!G14>'impto renta'!C14,'impto renta'!G14<'impto renta'!D14),'impto renta'!H14,IF(AND('impto renta'!G15>'impto renta'!C15,'impto renta'!G15<'impto renta'!D15),'impto renta'!H15,0))))))),-3) -> 116647000
A18: renta presentiva renta + pensión | E18: =ROUND(IF(AND('impto renta'!I9>'impto renta'!C9,'impto renta'!I9<'impto renta'!D9),'impto renta'!J9,IF(AND('impto renta'!I10>'impto renta'!C10,'impto renta'!I10<'impto renta'!D10),'impto renta'!J10,IF(AND('impto renta'!I11>'impto renta'!C11,'impto renta'!I11<'impto renta'!D11),'impto renta'!J11,IF(AND('impto renta'!I12>'impto renta'!C12,'impto renta'!I12<'impto renta'!D12),'impto renta'!J12,IF(AND('impto renta'!I13>'impto renta'!C13,'impto renta'!I13<'impto renta'!D13),'impto renta'!J13,IF(AND('impto renta'!I14>'impto renta'!C14,'impto renta'!I14<'impto renta'!D14),'impto renta'!J14,IF(AND('impto renta'!I15>'impto renta'!C15,'impto renta'!I15<'impto renta'!D15),'impto renta'!J15,0))))))),-3) -> 0
A23: Por dividendos y participaciones año 2016 (base casilla 76)
A24: Renta líquida sobre dividendos gravados 2016 y anteriores | E24: ='FORMULARIO 210'!J41 -> 25000000
A25: En UVT | E25: =E24/$E$2 -> 531.18028
A26: Valor del impuesto de renta | E26: =MAX(E31:E34) -> 0
A29: Rangos en UVT | C29: Tarifa marginal | D29: Impuesto | E29: IMPUESTO SOBRE LA RENTA POR DIVIDENDOS 2016 Y ANTERIORES
A30: Desde | B30: Hasta
A31: >0 | B31: 1090 | C31: 0 | D31: 0 | E31: 0
A32: >1,090 | B32: 1700 | C32: 0.19 | D32: (Base gravable en UVT menos 1.090 UVT) X 19% | E32: =IF(E25>1090,(IF(E25<=1700,ROUND((((+E25-1090)*19%)*E2),-3),0)),0) -> 0
A33: >1,700 | B33: 4100 | C33: 0.28 | D33: (Base gravable en UVT menos 1.700 UVT) X 28% + 116 UVT | E33: =IF(E25>1700,IF(E25<=4100,ROUND((((+E25-1700)*28%)*E2)+(116*E2),-3),0),0) -> 0
A34: >4,100 | B34: En adelante | C34: 0.33 | D34: (Base gravable en UVT menos 4.100 UVT) X 33% + 788 UVT | E34: =IF(E25>4100,ROUND((((+E25-4100)*33%)*E2)+(788*E2),-3),0) -> 0
A37: Valor primera subcedula Renglón 107 | E37: ='FORMULARIO 210'!J42 -> 50000000
A38: En UVT | E38: 0
A39: Valor del impuesto en pesos | E39: =ROUND(MAX(E43:E44),-3) -> 0
A41: Rangos en UVT | C41: Tarifa marginal | D41: Impuesto | E41: Determinación del impuesto de renta primera subcédula | F41: Determinación del impuesto de renta segunda subcédula
A42: Desde | B42: Hasta
A43: >0 | B43: 300 | C43: 0 | D43: 0 | E43: 0 | F43: 0
A44: >300 | B44: en Adelante | C44: 0.1 | D44: (Dividendos en UVT menos 300 UVT) X 10% | E44: =IF(E38>300,((E38-300)*10%)*E2,0) -> 0 | F44: =IF(E49>300,((E49-300)*10%)*E2,0) -> 0
A46: Valor segunda subcédula (Renglones 108) | E46: ='FORMULARIO 210'!J43 -> 43000000
A47: Valor primera parte del impuesto 35% | E47: =E46*0.35 -> 15050000
A48: Subtotal | E48: =E46-E47 -> 27950000
A49: En UVT | E49: 0
A50: Valor segunda parte del impuesto | E50: 0
A51: Valor total impuesto segunda subcédula | E51: =ROUND((E50+E47),-3) -> 15050000

Sheet dtos tribut
B2: Por impuesto Pagados en el Exterior | E2: =ROUND(SUM(D3:D5),-3) -> 0
B3: Impuestos pagados en el exterior
D5: 0
B6: Por Donaciones | E6: =ROUND(SUM(D7:D9),-3) -> 10000000
D7: =C7*0.25 -> 0
B8: Comunidad Santa Ana | C8: 40000000 | D8: =C8*0.25 -> 10000000
D9: =C9*0.25 -> 0
B10: Otros descuentos tributarios | E10: =ROUND(SUM(D11:D13),-3) -> 0
B14: Descuento dividendos
B15: Por dividendos no gravados y exceso sobre los gravados 2017 y siguientes | E15: =ROUND((((('C divid.'!F17+'C divid.'!F25-'FORMULARIO 210'!Y36)/'impto renta'!E2)-1090)*19%)*'impto renta'!E2,-3) -> 5063000
B20: Descuento por impuestos pagados en el exterior por ganancias ocasionales | E20: =ROUND(SUM(D21:D23),-3) -> 0

Sheet retefuente
B1: RETENCIONES EN LA FUENTE QUE LE PRACTICARON
C2: Agente retenedor | D2: Valor | E2: Total
B3: Renglón 133 | D3: 0 | E3: =ROUND(SUM(D3:D36),-3) -> 20820000
C4: Itgs Sas | D4: 13450000
C5: Banco davivienda | D5: 1500000
C6: Banco caja social | D6: 700000
C7: Secretaria de hacienda (vehiculo) | D7: =67000000*1% -> 670000
C8: Otros | D8: 4500000
D9: 0
D10: 0
D11: 0
D12: 0
D13: 0

Sheet anticipo
B1: CÁLCULO DEL ANTICIPO DE RENTA POR EL AÑO GRAVABLE 2025
C3: Registre el valor del saldo a favor no solicitado en devolución casilla 138 declaración renta 2024 | E3: 0
C4: Registre el valor del anticipo para la renta 2025, registrado en la casilla 134 declaración renta año 2024 | E4: 8700000
B5: Renglón 134 | C5: Registre el valor del impuesto neto de renta registrado en la casilla 127 declaración renta año 2024 | E5: 18000000
C6: Para el anticipo digite: 1 declaración por primera vez; 2 declaración por segunda vez; 3 declara por tercera y siguientes años; 4 declaración del año corriente es la última que presenta. | E6: 3
C7: Primer año | D7: Impuesto neto de renta año corriente | E7: {='FORMULARIO 210'!Y42:AB42} -> 116634000 | F7: 0 | G7: 0 | H7: 0
D8: 0.25 | E8: =ROUND(+E7*D8,-3) -> 29159000
D9: Menos: retenciones en la fuente | E9: =retefuente!E3 -> 20820000
D10: Total anticipo para el año 2026 | E10: =IF(E6=1,IF(E8-E9>0,E8-E9,0),0) -> 0
C11: Segundo año | D11: 1) Método del promedio
D12: Impuesto neto de renta año anterior | E12: =+E5 -> 18000000
D13: =D7 -> Impuesto neto de renta año corriente | E13: =+E7 -> 116634000
D14: Subtotal | E14: =+E12+E13 -> 134634000
D15: Promedio | E15: =ROUND(+E14/2,-3) -> 67317000
D16: 0.5 | E16: =ROUND(+E15*D16,-3) -> 33659000
D17: Menos: Retenciones en la fuente | E17: =+E9 -> 20820000
D18: Anticipo método del promedio | E18: =IF(E6=2,IF(E16-E17>0,E16-E17,0),0) -> 0
D19: 2) Método directo
D20: =D13 -> Impuesto neto de renta año corriente | E20: =+E7 -> 116634000
D21: 0.5 | E21: =ROUND(+E20*D21,-3) -> 58317000
D22: Menos: retenciones en la fuente | E22: =+E9 -> 20820000
D23: Anticipo método directo | E23: =IF(E6=2,IF(E21-E22>0,E21-E22,0),0) -> 0
D24: Total anticipo para el año 2026 | E24: =IF(E18>E23,E23,E18) -> 0
C25: Tercer y siguientes años | D25: 1) Método del promedio
D26: Impuesto neto de renta año anterior | E26: =+E5 -> 18000000
D27: =D20 -> Impuesto neto de renta año corriente | E27: =+E7 -> 116634000
D28: Subtotal | E28: =SUM(E26:E27) -> 134634000
D29: Promedio | E29: =ROUND((E28/2),-3) -> 67317000
D30: 0.75 | E30: =ROUND(+E29*D30,-3) -> 50488000
D31: Menos: retenciones en la fuente | E31: =+E9 -> 20820000
D32: Anticipo método del promedio | E32: =IF(E6=3,IF(E30-E31>0,E30-E31,0),0) -> 29668000
D33: 2) Método directo
D34: =D27 -> Impuesto neto de renta año corriente | E34: =+E7 -> 116634000
D35: 0.75 | E35: =ROUND(+E34*D35,-3) -> 87476000
D36: Menos: retenciones en la fuente | E36: =+E9 -> 20820000
D37: Anticipo método directo | E37: =IF(E6=3,IF(E35-E36>0,E35-E36,0),0) -> 66656000
D38: Total anticipo para el año 2026 | E38: =IF(E32>E37,E37,E32) -> 29668000
C40: Valor anticipo definitivo para el impuesto de renta año 2026 | E40: =IF(E10>0,E10,IF(E24>0,E24,IF(E38>0,E38,0))) -> 29668000
